Workbook

Sheet ИСХОД. ДАННЫЕ
A1: DR_Dat | B1: DR_Tim | C1: DR_NChk | D1: DR_NDoc | E1: DR_Apt | F1: DR_Kkm | G1: DR_TDoc | H1: DR_TPay | I1: DR_CDrugs | J1: DR_NDrugs | K1: DR_Suppl | L1: DR_Prod | M1: DR_Kol | N1: DR_Czak(закуп цена) | O1: DR_Croz (розничная цена) | P1: DR_Sdisc (сумма скидки) | Q1: DR_CDisc | R1: DR_BCDisc | S1: DR_TabEmpl | T1: DR_VZak | U1: DR_Pos
A2: 44774 | B2: 0.33770833 | C2: 1272 | D2: 13002561 | E2: 13 | F2: 22589 | G2: Розничная реализация | H2: 18 | I2: 144734 | J2: ГАСТАЛ №12 ТАБ. Д/РАСС. | K2: Пульс | L2: TEVA Pharvaceutical Industries Ltd | M2: 1 | N2: 196.71 | O2: 270 | P2: 0 | Q2: NULL | R2: NULL | S2: 29 | T2: 1 | U2: 1 | W2: 1. месячная оборачиваемость
A3: 44774 | B3: 0.36033565 | C3: 1273 | D3: 13002561 | E3: 13 | F3: 22589 | G3: Розничная реализация | H3: 15 | I3: 69661 | J3: ТОБРОПТ 0,3% 5МЛ. №1 ГЛ.КАПЛИ ФЛ./КАП. /РОМФАРМ/ | K3: Пульс | L3: РОМФАРМ КОМПАНИ ( ROMPHARM ) | M3: 1 | N3: 106.21 | O3: 127 | P3: 6 | Q3: 9 | R3: 200010004357 | S3: 29 | T3: 1 | U3: 1
A4: 44774 | B4: 0.37196759 | C4: 1274 | D4: 13002561 | E4: 13 | F4: 22589 | G4: Розничная реализация | H4: 18 | I4: 190635 | J4: ЭЛИКВИС 5МГ. №60 ТАБ. П/П/О /ПФАЙЗЕР/БРИСТОЛ-МАЙЕРС/ | K4: ГРАНД КАПИТАЛ СМОЛЕНСК ООО ФК | L4: Пфайзер | M4: 1 | N4: 2320.99 | O4: 2563 | P4: 76 | Q4: 9 | R4: 200010018491 | S4: 29 | T4: 1 | U4: 1 | W4: Обратите внимание, у вас появилась новая метрика для анализа - месячная оборачиваемость. Считайте ее как среднедневное количество продаж умноженное на 30 дней. Эта метрика показывает, сколько штук товара в месяц мы потенциально можем продать.
A5: 44774 | B5: 0.37546296 | C5: 1275 | D5: 13002561 | E5: 13 | F5: 22589 | G5: Розничная реализация | H5: 18 | I5: 276370 | J5: АРБИДОЛ МАКСИМУМ 200МГ. №10 КАПС. /ОТИСИФАРМ/ФАРМСТАНДАРТ/ | K5: Пульс | L5: ОТИСИФАРМ ПАО | M5: 1 | N5: 445.39 | O5: 541 | P5: 0 | Q5: NULL | R5: NULL | S5: 29 | T5: 1 | U5: 1
A6: 44774 | B6: 0.37783565 | C6: 1276 | D6: 13002561 | E6: 13 | F6: 22589 | G6: Розничная реализация | H6: 15 | I6: 2303 | J6: ЭНАМ 2,5МГ. №20 ТАБ. /Д-Р РЕДДИ/ | K6: Протек | L6: Д-р Редди с Лабораторис Лтд / Dr.REDDY's | M6: 1 | N6: 18.04 | O6: 22 | P6: 1 | Q6: 9 | R6: 200010000734 | S6: 29 | T6: 1 | U6: 5
A7: 44774 | B7: 0.37783565 | C7: 1276 | D7: 13002561 | E7: 13 | F7: 22589 | G7: Розничная реализация | H7: 15 | I7: 2303 | J7: ЭНАМ 2,5МГ. №20 ТАБ. /Д-Р РЕДДИ/ | K7: Протек | L7: Д-р Редди с Лабораторис Лтд / Dr.REDDY's | M7: 1 | N7: 18.04 | O7: 22 | P7: 1 | Q7: 9 | R7: 200010000734 | S7: 29 | T7: 1 | U7: 6
A8: 44774 | B8: 0.37783565 | C8: 1276 | D8: 13002561 | E8: 13 | F8: 22589 | G8: Розничная реализация | H8: 15 | I8: 338588 | J8: КЛОПИДОГРЕЛ-СЗ 75МГ. №28 ТАБ. П/П/О /СЕВЕРНАЯ ЗВЕЗДА/ | K8: Пульс | L8: Северная Звезда | M8: 1 | N8: 383.7 | O8: 475 | P8: 23 | Q8: 9 | R8: 200010000734 | S8: 29 | T8: 1 | U8: 3
A9: 44774 | B9: 0.37783565 | C9: 1276 | D9: 13002561 | E9: 13 | F9: 22589 | G9: Розничная реализация | H9: 15 | I9: 397616 | J9: КО-ВАМЛОСЕТ 5МГ.+160МГ.+12,5МГ. №30 ТАБ. П/П/О | K9: Протек | L9: КРКА-Рус ООО (KRKA ) | M9: 1 | N9: 536.82 | O9: 693 | P9: 48 | Q9: 9 | R9: 200010000734 | S9: 29 | T9: 1 | U9: 4
A10: 44774 | B10: 0.37783565 | C10: 1276 | D10: 13002561 | E10: 13 | F10: 22589 | G10: Розничная реализация | H10: 15 | I10: 338492 | J10: АТОРВАСТАТИН-СЗ 20МГ. №60 ТАБ. П/П/О /СЕВЕРНАЯ ЗВЕЗДА/ | K10: Протек | L10: Северная Звезда | M10: 1 | N10: 334.29 | O10: 418 | P10: 20 | Q10: 9 | R10: 200010000734 | S10: 29 | T10: 1 | U10: 1
A11: 44774 | B11: 0.37783565 | C11: 1276 | D11: 13002561 | E11: 13 | F11: 22589 | G11: Розничная реализация | H11: 15 | I11: 338479 | J11: АТОРВАСТАТИН-СЗ 40МГ. №30 ТАБ. П/П/О /СЕВЕРНАЯ ЗВЕЗДА/ | K11: Пульс | L11: Северная Звезда | M11: 1 | N11: 282.52 | O11: 340 | P11: 17 | Q11: 9 | R11: 200010000734 | S11: 29 | T11: 1 | U11: 2
A12: 44774 | B12: 0.37849537 | C12: 1277 | D12: 13002561 | E12: 13 | F12: 22589 | G12: Розничная реализация | H12: 18 | I12: 122156 | J12: КСИМЕЛИН ЭКСТРА 84МКГ/ДОЗА+70МКГ/ДОЗА 10МЛ. №1 НАЗАЛ.СПРЕЙ ДОЗИР. ФЛ. | K12: Пульс | L12: ТАКЕДА ФАРМАСЬЮТИКАЛ КОМПАНИ ЛИМИТЕД | M12: 1 | N12: 210.25 | O12: 284 | P12: 0 | Q12: NULL | R12: NULL | S12: 29 | T12: 1 | U12: 1
A13: 44774 | B13: 0.38320602 | C13: 1278 | D13: 13002561 | E13: 13 | F13: 22589 | G13: Розничная реализация | H13: 15 | I13: 608487 | J13: NF ВАТА ХИРУРГ. СТЕР. 100Г. /НЬЮФАРМ/ | K13: Фармкомплект ООО | L13: НьюФарм | M13: 1 | N13: 43.29 | O13: 71 | P13: 7 | Q13: 9 | R13: 200010001758 | S13: 29 | T13: 1 | U13: 1
A14: 44774 | B14: 0.38320602 | C14: 1278 | D14: 13002561 | E14: 13 | F14: 22589 | G14: Розничная реализация | H14: 15 | I14: 528004 | J14: СТОПСЕПТ ПЛЮС 90% 100МЛ. ДЕЗ.СР-ВО ФЛ. | K14: Авеста | L14: ГИППОКРАТ ООО | M14: 1 | N14: 35.52 | O14: 58 | P14: 5 | Q14: 9 | R14: 200010001758 | S14: 29 | T14: 1 | U14: 2
A15: 44774 | B15: 0.38756944 | C15: 1279 | D15: 13002561 | E15: 13 | F15: 22589 | G15: Розничная реализация | H15: 15 | I15: 443174 | J15: ПАСКАЛЬ ШПРИЦ 3-Х КОМП. 2МЛ. С ИГЛОЙ 23G 0,6Х30ММ. №10 [PASCAL] | K15: Катрен г.Химки | L15: ПАСКАЛЬ МЕДИКАЛ | M15: 1 | N15: 65.13 | O15: 103 | P15: 0 | Q15: NULL | R15: NULL | S15: 29 | T15: 1 | U15: 1
A16: 44774 | B16: 0.44326389 | C16: 1294 | D16: 13002561 | E16: 13 | F16: 22589 | G16: Розничная реализация | H16: 18 | I16: 443174 | J16: ПАСКАЛЬ ШПРИЦ 3-Х КОМП. 2МЛ. С ИГЛОЙ 23G 0,6Х30ММ. №10 [PASCAL] | K16: Катрен г.Химки | L16: ПАСКАЛЬ МЕДИКАЛ | M16: 1 | N16: 65.13 | O16: 103 | P16: 0 | Q16: NULL | R16: NULL | S16: 29 | T16: 1 | U16: 3
A17: 44774 | B17: 0.39586806 | C17: 1280 | D17: 13002561 | E17: 13 | F17: 22589 | G17: Розничная реализация | H17: 15 | I17: 21372 | J17: КЛОТРИМАЗОЛ 1% 20Г. КРЕМ Д/НАРУЖ.ПРИМ. ТУБА /ХИПЕРИОН/РУМЫНИЯ/ | K17: Пульс | L17: HYPERION SA (ХИПЕРИОН ) | M17: 1 | N17: 86.28 | O17: 123 | P17: 0 | Q17: NULL | R17: NULL | S17: 29 | T17: 1 | U17: 1
A18: 44774 | B18: 0.39586806 | C18: 1280 | D18: 13002561 | E18: 13 | F18: 22589 | G18: Розничная реализация | H18: 15 | I18: 365627 | J18: РИНОНОРМ-ТЕВА 0,1% 140МКГ/ДОЗА 20МЛ. НАЗАЛ.СПРЕЙ ФЛ. /ТЕВА/ | K18: ГРАНД КАПИТАЛ СМОЛЕНСК ООО ФК | L18: ТЕВА ЧЕШСКОЕ ПРЕДПРИЯТИЕ | M18: 1 | N18: 78.24 | O18: 96 | P18: 0 | Q18: NULL | R18: NULL | S18: 29 | T18: 1 | U18: 2
A19: 44774 | B19: 0.68071759 | C19: 1373 | D19: 13002561 | E19: 13 | F19: 22589 | G19: Розничная реализация | H19: 18 | I19: 365627 | J19: РИНОНОРМ-ТЕВА 0,1% 140МКГ/ДОЗА 20МЛ. НАЗАЛ.СПРЕЙ ФЛ. /ТЕВА/ | K19: ГРАНД КАПИТАЛ СМОЛЕНСК ООО ФК | L19: ТЕВА ЧЕШСКОЕ ПРЕДПРИЯТИЕ | M19: 1 | N19: 78.24 | O19: 96 | P19: 0 | Q19: NULL | R19: NULL | S19: 29 | T19: 1 | U19: 1
A20: 44774 | B20: 0.40825231 | C20: 1281 | D20: 13002561 | E20: 13 | F20: 22589 | G20: Розничная реализация | H20: 15 | I20: 12625 | J20: ДЮФАЛАК 667МГ/МЛ. 500МЛ. СИРОП ФЛ. +МЕРН.СТАКАН /ЭББОТТ/СОЛВЕЙ/ | K20: Арал плюс | L20: Abbott Japan Co ( ЭББОТТ ) | M20: 1 | N20: 455.9 | O20: 553 | P20: 16 | Q20: 9 | R20: 200010001617 | S20: 29 | T20: 1 | U20: 1
A21: 44774 | B21: 0.41150463 | C21: 1282 | D21: 13002561 | E21: 13 | F21: 22589 | G21: Розничная реализация | H21: 18 | I21: 67565 | J21: ГЕЛАДРИНК ФОРТЕ ПОР. Д/ПРИЕМА ВНУТРЬ АПЕЛЬСИН 420Г. БАНКА | K21: ВИТТА КОМПАНИ ООО | L21: ОРЛИНГ | M21: 1 | N21: 3638.1 | O21: 4985 | P21: 498 | Q21: 9 | R21: 200010004830 | S21: 29 | T21: 1 | U21: 1
A22: 44774 | B22: 0.41150463 | C22: 1282 | D22: 13002561 | E22: 13 | F22: 22589 | G22: Розничная реализация | H22: 18 | I22: 507949 | J22: ПИРАЦЕТАМ 200МГ. №60 ТАБ. П/П/О /ОБНОВЛЕНИЕ/ | K22: ГК Надежда Фарм | L22: ОБНОВЛЕНИЕ ПФК | M22: 1 | N22: 60.22 | O22: 73 | P22: 3 | Q22: 9 | R22: 200010004830 | S22: 29 | T22: 1 | U22: 2
A23: 44774 | B23: 0.4140162 | C23: 1283 | D23: 13002561 | E23: 13 | F23: 22589 | G23: Розничная реализация | H23: 15 | I23: 461654 | J23: МАГНЕЛИС В6 №120 ТАБ. П/О | K23: Катрен г.Химки | L23: ФАРМСТАНДАРТ УФАВИТА | M23: 1 | N23: 677.2 | O23: 779 | P23: 54 | Q23: 9 | R23: 200010020913 | S23: 29 | T23: 1 | U23: 2
A24: 44774 | B24: 0.4140162 | C24: 1283 | D24: 13002561 | E24: 13 | F24: 22589 | G24: Розничная реализация | H24: 15 | I24: 7697 | J24: МЕЗИМ-ФОРТЕ №80 ТАБ. П/О /БЕРЛИН-ХЕМИ/ | K24: Пульс | L24: Берлин-Хеми АГ/Менарини Групп (Menarini ) | M24: 1 | N24: 248.34 | O24: 302 | P24: 15 | Q24: 9 | R24: 200010020913 | S24: 29 | T24: 1 | U24: 3
A25: 44774 | B25: 0.4140162 | C25: 1283 | D25: 13002561 | E25: 13 | F25: 22589 | G25: Розничная реализация | H25: 15 | I25: 340968 | J25: КАЛЬЦИЙ Д3 НИКОМЕД 500МГ.+200МЕ №60 КЛУБНИКА+АРБУЗ ТАБ.ЖЕВ. | K25: Пульс | L25: ТАКЕДА ФАРМАСЬЮТИКАЛ КОМПАНИ ЛИМИТЕД | M25: 1 | N25: 403.68 | O25: 533 | P25: 37 | Q25: 9 | R25: 200010020913 | S25: 29 | T25: 1 | U25: 1
A26: 44774 | B26: 0.41548611 | C26: 1284 | D26: 13002561 | E26: 13 | F26: 22589 | G26: Розничная реализация | H26: 15 | I26: 530607 | J26: ЭКСПРЕСС-ТЕСТ НА А/ТЕЛА COVID-19 LGG/LGM | K26: Арал плюс | L26: ИМТЭК ООО | M26: 2 | N26: 619.88 | O26: 862 | P26: 172 | Q26: 9 | R26: 200010017394 | S26: 29 | T26: 1 | U26: 1
A27: 44774 | B27: 0.41795139 | C27: 1285 | D27: 13002561 | E27: 13 | F27: 22589 | G27: Розничная реализация | H27: 18 | I27: 330172 | J27: БОБС ЛЕДЕНЦЫ Д/ГОРЛА 35Г. ЭКСТРА МЕНТОЛ №10 | K27: Протек | L27: МАК-ИВАНОВО | M27: 1 | N27: 23.98 | O27: 39 | P27: 0 | Q27: NULL | R27: NULL | S27: 29 | T27: 1 | U27: 1
A28: 44774 | B28: 0.41947917 | C28: 1286 | D28: 13002561 | E28: 13 | F28: 22589 | G28: Розничная реализация | H28: 18 | I28: 393315 | J28: ЦИТРАМОН П №10 ТАБ. /ФАРМСТАНДАРТ/ | K28: Катрен г.Химки | L28: ФАРМСТАНДАРТ ЛЕКСРЕДСТВА ОАО | M28: 1 | N28: 16.21 | O28: 25 | P28: 0 | Q28: NULL | R28: NULL | S28: 29 | T28: 1 | U28: 1
A29: 44774 | B29: 0.41947917 | C29: 1286 | D29: 13002561 | E29: 13 | F29: 22589 | G29: Розничная реализация | H29: 18 | I29: 393315 | J29: ЦИТРАМОН П №10 ТАБ. /ФАРМСТАНДАРТ/ | K29: Катрен г.Химки | L29: ФАРМСТАНДАРТ ЛЕКСРЕДСТВА ОАО | M29: 1 | N29: 16.21 | O29: 25 | P29: 0 | Q29: NULL | R29: NULL | S29: 29 | T29: 1 | U29: 2
A30: 44774 | B30: 0.62164352 | C30: 1362 | D30: 13002561 | E30: 13 | F30: 22589 | G30: Розничная реализация | H30: 18 | I30: 393315 | J30: ЦИТРАМОН П №10 ТАБ. /ФАРМСТАНДАРТ/ | K30: Катрен г.Химки | L30: ФАРМСТАНДАРТ ЛЕКСРЕДСТВА ОАО | M30: 1 | N30: 16.21 | O30: 25 | P30: 0 | Q30: NULL | R30: NULL | S30: 29 | T30: 1 | U30: 3
A31: 44774 | B31: 0.42930556 | C31: 1287 | D31: 13002561 | E31: 13 | F31: 22589 | G31: Розничная реализация | H31: 18 | I31: 377588 | J31: ТИЗИН КЛАССИК 0,1% 10МЛ. НАЗАЛ.СПРЕЙ ФЛ. /ДЖОНСОН/ | K31: Катрен г.Химки | L31: ДЕЛЬФАРМ ОРЛЕАН ( DELPHARM ) | M31: 1 | N31: 84.17 | O31: 100 | P31: 41.09 | Q31: 925 | R31: 200000000492 | S31: 29 | T31: 1 | U31: 3
A32: 44774 | B32: 0.42930556 | C32: 1287 | D32: 13002561 | E32: 13 | F32: 22589 | G32: Розничная реализация | H32: 18 | I32: 297336 | J32: ЛАКОМКА ПОМАДА ГИГИЕН. ЯГОДНЫЙ МИКС 2,8Г. /АВАНТА/ | K32: Протек | L32: АВАНТА ОАО | M32: 1 | N32: 45.17 | O32: 74 | P32: 30.41 | Q32: 925 | R32: 200000000492 | S32: 29 | T32: 1 | U32: 1
A33: 44774 | B33: 0.42930556 | C33: 1287 | D33: 13002561 | E33: 13 | F33: 22589 | G33: Розничная реализация | H33: 18 | I33: 2302 | J33: ОМЕЗ 20МГ. №30 КАПС. /Д-Р РЕДДИ/ | K33: ВИТТА КОМПАНИ ООО | L33: ДОКТОР РЕДДИ С ЛАБ / Dr. REDDY's ) | M33: 1 | N33: 148.28 | O33: 174 | P33: 71.5 | Q33: 925 | R33: 200000000492 | S33: 29 | T33: 1 | U33: 2
A34: 44774 | B34: 0.43451389 | C34: 1288 | D34: 13002561 | E34: 13 | F34: 22589 | G34: Розничная реализация | H34: 15 | I34: 23396 | J34: ЭВКАЛИПТ М №24 ПАСТИЛКИ | K34: ООО "Акцентмед" | L34: ДР.АУФДЕРМАУР АГ | M34: 2 | N34: 248.26 | O34: 336 | P34: 0 | Q34: NULL | R34: NULL | S34: 29 | T34: 1 | U34: 1
A35: 44774 | B35: 0.43633102 | C35: 1289 | D35: 13002561 | E35: 13 | F35: 22589 | G35: Розничная реализация | H35: 15 | I35: 143150 | J35: АЗАРГА 10МГ/МЛ.+5МГ/МЛ. 5МЛ. №1 ГЛ.КАПЛИ ФЛ./КАП. | K35: ВИТТА КОМПАНИ ООО | L35: АЛКОН Куврер н.в. (ALCON ) | M35: 1 | N35: 1042.25 | O35: 1314 | P35: 91 | Q35: 9 | R35: 200010000065 | S35: 29 | T35: 1 | U35: 1
A36: 44774 | B36: 0.43633102 | C36: 1289 | D36: 13002561 | E36: 13 | F36: 22589 | G36: Розничная реализация | H36: 15 | I36: 263189 | J36: ТРАВАТАН 0,004% 2,5МЛ. №3 ГЛ.КАПЛИ ФЛ./КАП. | K36: Катрен г.Химки | L36: ALCON COUVREUR (АЛКОН ) | M36: 1 | N36: 1576.65 | O36: 1971 | P36: 137 | Q36: 9 | R36: 200010000065 | S36: 29 | T36: 1 | U36: 5
A37: 44774 | B37: 0.43633102 | C37: 1289 | D37: 13002561 | E37: 13 | F37: 22589 | G37: Розничная реализация | H37: 15 | I37: 519407 | J37: ЙОДА 5% 10МЛ. СПИРТ. Р-Р ФЛ. /ЯРОСЛАВСКАЯ ФФ/ | K37: Катрен г.Химки | L37: ЯРОСЛАВСКАЯ ФАРМ. ФАБРИКА | M37: 1 | N37: 34.25 | O37: 53 | P37: 3 | Q37: 9 | R37: 200010000065 | S37: 29 | T37: 1 | U37: 2
A38: 44774 | B38: 0.43633102 | C38: 1289 | D38: 13002561 | E38: 13 | F38: 22589 | G38: Розничная реализация | H38: 15 | I38: 345211 | J38: ОМЕПРАЗОЛ 20МГ. №30 КАПС. /ПРОИЗВОДСТВО МЕДИКАМЕНТОВ/ | K38: ГРАНД КАПИТАЛ СМОЛЕНСК ООО ФК | L38: ПРОИЗВОДСТВО МЕДИКАМЕНТОВ ООО | M38: 1 | N38: 25.28 | O38: 30 | P38: 1 | Q38: 9 | R38: 200010000065 | S38: 29 | T38: 1 | U38: 3
A39: 44774 | B39: 0.47800926 | C39: 1307 | D39: 13002561 | E39: 13 | F39: 22589 | G39: Розничная реализация | H39: 18 | I39: 345211 | J39: ОМЕПРАЗОЛ 20МГ. №30 КАПС. /ПРОИЗВОДСТВО МЕДИКАМЕНТОВ/ | K39: ГРАНД КАПИТАЛ СМОЛЕНСК ООО ФК | L39: ПРОИЗВОДСТВО МЕДИКАМЕНТОВ ООО | M39: 1 | N39: 25.28 | O39: 30 | P39: 1 | Q39: 9 | R39: 200010000452 | S39: 29 | T39: 1 | U39: 1
A40: 44774 | B40: 0.50565972 | C40: 1319 | D40: 13002561 | E40: 13 | F40: 22589 | G40: Розничная реализация | H40: 18 | I40: 345211 | J40: ОМЕПРАЗОЛ 20МГ. №30 КАПС. /ПРОИЗВОДСТВО МЕДИКАМЕНТОВ/ | K40: ГРАНД КАПИТАЛ СМОЛЕНСК ООО ФК | L40: ПРОИЗВОДСТВО МЕДИКАМЕНТОВ ООО | M40: 1 | N40: 25.28 | O40: 30 | P40: 1 | Q40: 9 | R40: 200010015482 | S40: 29 | T40: 1 | U40: 3
A41: 44774 | B41: 0.43633102 | C41: 1289 | D41: 13002561 | E41: 13 | F41: 22589 | G41: Розничная реализация | H41: 15 | I41: 1504015 | J41: ПАКЕТ | K41: Индивидуальный предприниматель Кочанов Андрей Миха | L41: ПРОИЗВОДСТВО МЕДИКАМЕНТОВ ООО | M41: 1 | N41: 1.15 | O41: 2 | P41: 0 | Q41: NULL | R41: NULL | S41: 29 | T41: 1 | U41: 4
A42: 44774 | B42: 0.43896991 | C42: 1290 | D42: 13002561 | E42: 13 | F42: 22589 | G42: Розничная реализация | H42: 15 | I42: 1504015 | J42: ПАКЕТ | K42: Индивидуальный предприниматель Кочанов Андрей Миха | L42: ПРОИЗВОДСТВО МЕДИКАМЕНТОВ ООО | M42: 1 | N42: 1.15 | O42: 2 | P42: 0 | Q42: NULL | R42: NULL | S42: 29 | T42: 1 | U42: 4
A43: 44774 | B43: 0.44123843 | C43: 1292 | D43: 13002561 | E43: 13 | F43: 22589 | G43: Розничная реализация | H43: 18 | I43: 1504015 | J43: ПАКЕТ | K43: Индивидуальный предприниматель Кочанов Андрей Миха | L43: ПРОИЗВОДСТВО МЕДИКАМЕНТОВ ООО | M43: 1 | N43: 1.15 | O43: 2 | P43: 0 | Q43: NULL | R43: NULL | S43: 29 | T43: 1 | U43: 3
A44: 44774 | B44: 0.44861111 | C44: 1297 | D44: 13002561 | E44: 13 | F44: 22589 | G44: Розничная реализация | H44: 15 | I44: 1504015 | J44: ПАКЕТ | K44: Индивидуальный предприниматель Кочанов Андрей Миха | L44: ПРОИЗВОДСТВО МЕДИКАМЕНТОВ ООО | M44: 1 | N44: 1.15 | O44: 2 | P44: 0 | Q44: NULL | R44: NULL | S44: 29 | T44: 1 | U44: 4
A45: 44774 | B45: 0.45111111 | C45: 1298 | D45: 13002561 | E45: 13 | F45: 22589 | G45: Розничная реализация | H45: 18 | I45: 1504015 | J45: ПАКЕТ | K45: Индивидуальный предприниматель Кочанов Андрей Миха | L45: ПРОИЗВОДСТВО МЕДИКАМЕНТОВ ООО | M45: 1 | N45: 1.15 | O45: 2 | P45: 0 | Q45: NULL | R45: NULL | S45: 29 | T45: 1 | U45: 4
A46: 44774 | B46: 0.51331019 | C46: 1324 | D46: 13002561 | E46: 13 | F46: 22589 | G46: Розничная реализация | H46: 15 | I46: 1504015 | J46: ПАКЕТ | K46: Индивидуальный предприниматель Кочанов Андрей Миха | L46: ПРОИЗВОДСТВО МЕДИКАМЕНТОВ ООО | M46: 1 | N46: 1.15 | O46: 2 | P46: 0 | Q46: NULL | R46: NULL | S46: 29 | T46: 1 | U46: 2
A47: 44774 | B47: 0.5237963 | C47: 1327 | D47: 13002561 | E47: 13 | F47: 22589 | G47: Розничная реализация | H47: 18 | I47: 1504015 | J47: ПАКЕТ | K47: Индивидуальный предприниматель Кочанов Андрей Миха | L47: ПРОИЗВОДСТВО МЕДИКАМЕНТОВ ООО | M47: 1 | N47: 1.15 | O47: 2 | P47: 0 | Q47: NULL | R47: NULL | S47: 29 | T47: 1 | U47: 4
A48: 44774 | B48: 0.6430787 | C48: 1367 | D48: 13002561 | E48: 13 | F48: 22589 | G48: Розничная реализация | H48: 18 | I48: 1504015 | J48: ПАКЕТ | K48: Индивидуальный предприниматель Кочанов Андрей Миха | L48: ПРОИЗВОДСТВО МЕДИКАМЕНТОВ ООО | M48: 1 | N48: 1.15 | O48: 2 | P48: 0 | Q48: NULL | R48: NULL | S48: 29 | T48: 1 | U48: 3
A49: 44774 | B49: 0.70020833 | C49: 1380 | D49: 13002561 | E49: 13 | F49: 22589 | G49: Розничная реализация | H49: 18 | I49: 1504015 | J49: ПАКЕТ | K49: Индивидуальный предприниматель Кочанов Андрей Миха | L49: ПРОИЗВОДСТВО МЕДИКАМЕНТОВ ООО | M49: 1 | N49: 1.15 | O49: 2 | P49: 0 | Q49: NULL | R49: NULL | S49: 29 | T49: 1 | U49: 5
A50: 44774 | B50: 0.78233796 | C50: 1402 | D50: 13002561 | E50: 13 | F50: 22589 | G50: Розничная реализация | H50: 18 | I50: 1504015 | J50: ПАКЕТ | K50: Индивидуальный предприниматель Кочанов Андрей Миха | L50: ПРОИЗВОДСТВО МЕДИКАМЕНТОВ ООО | M50: 1 | N50: 1.15 | O50: 2 | P50: 0 | Q50: NULL | R50: NULL | S50: 29 | T50: 1 | U50: 5
A51: 44774 | B51: 0.43896991 | C51: 1290 | D51: 13002561 | E51: 13 | F51: 22589 | G51: Розничная реализация | H51: 15 | I51: 497302 | J51: ПЕРЕКИСЬ ВОДОРОДА 3% 100МЛ. №1 Р-Р ДЕЗ.СР-ВО ФЛ. ПЛАСТ. /САМАРАМЕДПРОМ/ | K51: Катрен г.Химки | L51: Самарамедпром ОАО | M51: 2 | N51: 9.79 | O51: 16 | P51: 3 | Q51: 9 | R51: 200010000065 | S51: 29 | T51: 1 | U51: 6
A52: 44774 | B52: 0.43896991 | C52: 1290 | D52: 13002561 | E52: 13 | F52: 22589 | G52: Розничная реализация | H52: 15 | I52: 278599 | J52: ХЕЛП БИНТ СТЕР. 7МХ14СМ И/У [HELP] | K52: Пульс | L52: ЭВТЕКС | M52: 2 | N52: 30.62 | O52: 50 | P52: 10 | Q52: 9 | R52: 200010000065 | S52: 29 | T52: 1 | U52: 8
A53: 44774 | B53: 0.43896991 | C53: 1290 | D53: 13002561 | E53: 13 | F53: 22589 | G53: Розничная реализация | H53: 15 | I53: 50279 | J53: БИНТ СТЕР. 10МХ16СМ И/У | K53: Катрен г.Химки | L53: ЭВТЕКС | M53: 1 | N53: 45.13 | O53: 74 | P53: 7 | Q53: 9 | R53: 200010000065 | S53: 29 | T53: 1 | U53: 1
A54: 44774 | B54: 0.43896991 | C54: 1290 | D54: 13002561 | E54: 13 | F54: 22589 | G54: Розничная реализация | H54: 15 | I54: 142036 | J54: ПЕНТАЛГИН №24 ТАБ. П/П/О /ОТИСИФАРМ/ | K54: Пульс | L54: ФАРМСТАНДАРТ ЛЕКСРЕДСТВА ОАО | M54: 1 | N54: 187.36 | O54: 220 | P54: 15 | Q54: 9 | R54: 200010000065 | S54: 29 | T54: 1 | U54: 5
A55: 44774 | B55: 0.52601852 | C55: 1328 | D55: 13002561 | E55: 13 | F55: 22589 | G55: Розничная реализация | H55: 15 | I55: 142036 | J55: ПЕНТАЛГИН №24 ТАБ. П/П/О /ОТИСИФАРМ/ | K55: Пульс | L55: ФАРМСТАНДАРТ ЛЕКСРЕДСТВА ОАО | M55: 1 | N55: 187.36 | O55: 220 | P55: 0 | Q55: NULL | R55: NULL | S55: 29 | T55: 1 | U55: 4
A56: 44774 | B56: 0.43896991 | C56: 1290 | D56: 13002561 | E56: 13 | F56: 22589 | G56: Розничная реализация | H56: 15 | I56: 523194 | J56: НАЙЗ АКТИВГЕЛЬ 1% 50Г. №1 ГЕЛЬ Д/НАРУЖ.ПРИМ. ТУБА | K56: ГРАНД КАПИТАЛ СМОЛЕНСК ООО ФК | L56: Д-р Редди с Лабораторис Лтд / Dr.REDDY's | M56: 1 | N56: 320.39 | O56: 423 | P56: 29 | Q56: 9 | R56: 200010000065 | S56: 29 | T56: 1 | U56: 3
A57: 44774 | B57: 0.43896991 | C57: 1290 | D57: 13002561 | E57: 13 | F57: 22589 | G57: Розничная реализация | H57: 15 | I57: 460183 | J57: ГУБКА ГЕМОСТАТ. КОЛЛАГЕН. С СЕРЕБРОМ 50Х50Х7ММ №10 /ЗЕЛЕНАЯ ДУБРАВА/ | K57: Фармкомплект ООО | L57: ЗЕЛЕНАЯ ДУБРАВА | M57: 1 | N57: 64.71 | O57: 102 | P57: 10 | Q57: 9 | R57: 200010000065 | S57: 29 | T57: 1 | U57: 2
A58: 44774 | B58: 0.43896991 | C58: 1290 | D58: 13002561 | E58: 13 | F58: 22589 | G58: Розничная реализация | H58: 15 | I58: 168795 | J58: СТАТИН 1Г. №5 ПОР. ПАК. (Д/ОСТАНОВКИ КРОВОТЕЧЕНИЙ) | K58: Катрен г.Химки | L58: Пальма ООО | M58: 1 | N58: 73.77 | O58: 122 | P58: 12 | Q58: 9 | R58: 200010000065 | S58: 29 | T58: 1 | U58: 7
A59: 44774 | B59: 0.43967593 | C59: 1291 | D59: 13002561 | E59: 13 | F59: 22589 | G59: Розничная реализация | H59: 15 | I59: 269 | J59: ВАЛОКОРДИН 20МЛ. КАПЛИ Д/ПРИЕМА ВНУТРЬ ФЛ./КАП. | K59: ГРАНД КАПИТАЛ СМОЛЕНСК ООО ФК | L59: КРЕВЕЛЬ МОЙЗЕЛЬБАХ ГМБХ (KREWEL ) | M59: 1 | N59: 155.68 | O59: 195 | P59: 13 | Q59: 9 | R59: 200010004067 | S59: 29 | T59: 1 | U59: 2
A60: 44774 | B60: 0.43967593 | C60: 1291 | D60: 13002561 | E60: 13 | F60: 22589 | G60: Розничная реализация | H60: 15 | I60: 2289 | J60: L-ТИРОКСИН 100МКГ. №100 ТАБ. /БЕРЛИН ХЕМИ/ | K60: Магнит Фарма ООО | L60: Берлин-Хеми АГ/Менарини Групп (Menarini ) | M60: 1 | N60: 129.03 | O60: 153 | P60: 7 | Q60: 9 | R60: 200010004067 | S60: 29 | T60: 1 | U60: 1
A61: 44774 | B61: 0.44123843 | C61: 1292 | D61: 13002561 | E61: 13 | F61: 22589 | G61: Розничная реализация | H61: 18 | I61: 41348 | J61: КЕТОНАЛ 50МГ/МЛ. 2МЛ. №10 Р-Р Д/В/В,В/М АМП. /ЛЕК/ | K61: ГРАНД КАПИТАЛ СМОЛЕНСК ООО ФК | L61: Лек Д.Д. (LEK D.D. ) | M61: 1 | N61: 205.78 | O61: 247 | P61: 12 | Q61: 9 | R61: 200010020276 | S61: 29 | T61: 1 | U61: 2
A62: 44774 | B62: 0.44123843 | C62: 1292 | D62: 13002561 | E62: 13 | F62: 22589 | G62: Розничная реализация | H62: 18 | I62: 304 | J62: ВОЛЬТАРЕН 25МГ/МЛ. 3МЛ. №5 Р-Р Д/В/М АМП. /НОВАРТИС/ГЛАКСО/ | K62: ГРАНД КАПИТАЛ СМОЛЕНСК ООО ФК | L62: ЛЕК ФАРМАСЬЮТИКАЛЗ Д.Д. | M62: 1 | N62: 104.35 | O62: 125 | P62: 6 | Q62: 9 | R62: 200010020276 | S62: 29 | T62: 1 | U62: 1
A63: 44774 | B63: 0.44123843 | C63: 1292 | D63: 13002561 | E63: 13 | F63: 22589 | G63: Розничная реализация | H63: 18 | I63: 443170 | J63: ПАСКАЛЬ ШПРИЦ 3-Х КОМП. 3МЛ. С ИГЛОЙ 22G 0,7Х40ММ. №10 [PASCAL] | K63: Катрен г.Химки | L63: ПАСКАЛЬ МЕДИКАЛ | M63: 2 | N63: 57.11 | O63: 90 | P63: 18 | Q63: 9 | R63: 200010020276 | S63: 29 | T63: 1 | U63: 4
A64: 44774 | B64: 0.44200231 | C64: 1293 | D64: 13002561 | E64: 13 | F64: 22589 | G64: Розничная реализация | H64: 18 | I64: 19646 | J64: ШИПОВНИКА ПЛОДЫ 2Г. №20 ПАК. /КРАСНОГОРСК/ | K64: Здравсервис | L64: КРАСНОГОРСКЛЕКСРЕДСТВА ОАО | M64: 1 | N64: 88.91 | O64: 127 | P64: 0 | Q64: NULL | R64: NULL | S64: 29 | T64: 1 | U64: 1
A65: 44774 | B65: 0.44326389 | C65: 1294 | D65: 13002561 | E65: 13 | F65: 22589 | G65: Розничная реализация | H65: 18 | I65: 105888 | J65: АСЕПТИКА САЛФЕТКА СПИРТОВАЯ 60Х100 №20 | K65: Здравсервис | L65: АСЕПТИКА ООО | M65: 1 | N65: 35.77 | O65: 58 | P65: 0 | Q65: NULL | R65: NULL | S65: 29 | T65: 1 | U65: 1
A66: 44774 | B66: 0.57680556 | C66: 1348 | D66: 13002561 | E66: 13 | F66: 22589 | G66: Розничная реализация | H66: 15 | I66: 105888 | J66: АСЕПТИКА САЛФЕТКА СПИРТОВАЯ 60Х100 №20 | K66: Здравсервис | L66: АСЕПТИКА ООО | M66: 1 | N66: 35.77 | O66: 58 | P66: 5 | Q66: 9 | R66: 200010021953 | S66: 29 | T66: 1 | U66: 1
A67: 44774 | B67: 0.44326389 | C67: 1294 | D67: 13002561 | E67: 13 | F67: 22589 | G67: Розничная реализация | H67: 18 | I67: 345578 | J67: ПАРАЦЕТАМОЛ 500МГ. №20 ТАБ. /ФАРМСТАНДАРТ/ | K67: Катрен г.Химки | L67: ФАРМСТАНДАРТ ЛЕКСРЕДСТВА ОАО | M67: 1 | N67: 20.61 | O67: 25 | P67: 0 | Q67: NULL | R67: NULL | S67: 29 | T67: 1 | U67: 2
A68: 44774 | B68: 0.79040509 | C68: 1405 | D68: 13002561 | E68: 13 | F68: 22589 | G68: Розничная реализация | H68: 18 | I68: 345578 | J68: ПАРАЦЕТАМОЛ 500МГ. №20 ТАБ. /ФАРМСТАНДАРТ/ | K68: Катрен г.Химки | L68: ФАРМСТАНДАРТ ЛЕКСРЕДСТВА ОАО | M68: 1 | N68: 20.61 | O68: 25 | P68: 0 | Q68: NULL | R68: NULL | S68: 29 | T68: 1 | U68: 7
A69: 44774 | B69: 0.44326389 | C69: 1294 | D69: 13002561 | E69: 13 | F69: 22589 | G69: Розничная реализация | H69: 18 | I69: 338912 | J69: ЦИАНОКОБАЛАМИН 0,5МГ/МЛ. 1МЛ. №10 Р-Р Д/ИН. АМП. (ВИТАМИН В12) /ДАЛЬХИМФАРМ/ | K69: ВИТТА КОМПАНИ ООО | L69: Дальхимфарм ОАО | M69: 1 | N69: 37.95 | O69: 47.04 | P69: 0 | Q69: NULL | R69: NULL | S69: 29 | T69: 1 | U69: 4
A70: 44774 | B70: 0.44415509 | C70: 1295 | D70: 13002561 | E70: 13 | F70: 22589 | G70: Розничная реализация | H70: 15 | I70: 157466 | J70: Д.ТАЙСС АНГИ СЕПТ ЛИМОН №24 ТАБ. Д/РАСС. | K70: ГРАНД КАПИТАЛ СМОЛЕНСК ООО ФК | L70: Др. Тайсс Натурварен ГмбХ (THEISS ) | M70: 1 | N70: 169.99 | O70: 233 | P70: 16 | Q70: 9 | R70: 200010013040 | S70: 29 | T70: 1 | U70: 1
A71: 44774 | B71: 0.44601852 | C71: 1296 | D71: 13002561 | E71: 13 | F71: 22589 | G71: Розничная реализация | H71: 15 | I71: 74670 | J71: ПРОПОСОЛ 25Г. СПРЕЙ Д/МЕСТ.ПРИМ. БАЛЛОН /АЛТАЙВИТАМИНЫ/ | K71: ООО "Акцентмед" | L71: АЛТАЙВИТАМИНЫ | M71: 1 | N71: 93.55 | O71: 133 | P71: 9 | Q71: 9 | R71: 200010007414 | S71: 29 | T71: 1 | U71: 4
A72: 44774 | B72: 0.44601852 | C72: 1296 | D72: 13002561 | E72: 13 | F72: 22589 | G72: Розничная реализация | H72: 15 | I72: 468466 | J72: ИНГАВИРИН 90МГ. №10 КАПС. /ВАЛЕНТА/ | K72: Катрен г.Химки | L72: ВАЛЕНТА ФАРМ | M72: 1 | N72: 666.45 | O72: 739 | P72: 22 | Q72: 9 | R72: 200010007414 | S72: 29 | T72: 1 | U72: 2
A73: 44774 | B73: 0.44601852 | C73: 1296 | D73: 13002561 | E73: 13 | F73: 22589 | G73: Розничная реализация | H73: 15 | I73: 167293 | J73: ДОРИТРИЦИН №10 ТАБ. Д/РАСС. | K73: Пульс | L73: МЕДИЦЕ АРЦН.ПЮТТЕР | M73: 1 | N73: 360.47 | O73: 476 | P73: 33 | Q73: 9 | R73: 200010007414 | S73: 29 | T73: 1 | U73: 1
A74: 44774 | B74: 0.44601852 | C74: 1296 | D74: 13002561 | E74: 13 | F74: 22589 | G74: Розничная реализация | H74: 15 | I74: 954 | J74: ПИНОСОЛ 10МЛ. НАЗАЛ.КАПЛИ ФЛ./КАП. | K74: Фармкомплект ООО | L74: САНЕКА ФАРМАСЬЮТИКАЛС А.С. (SANECA ) | M74: 1 | N74: 206.7 | O74: 280 | P74: 19 | Q74: 9 | R74: 200010007414 | S74: 29 | T74: 1 | U74: 3
A75: 44774 | B75: 0.44861111 | C75: 1297 | D75: 13002561 | E75: 13 | F75: 22589 | G75: Розничная реализация | H75: 15 | I75: 8529 | J75: РИНОФЛУИМУЦИЛ 10МЛ. СПРЕЙ НАЗАЛ. ФЛ. /ЗАМБОН/ | K75: Пульс | L75: ZAMBON GROUP (ЗАМБОН ) | M75: 1 | N75: 299.66 | O75: 405 | P75: 0 | Q75: NULL | R75: NULL | S75: 29 | T75: 1 | U75: 5
A76: 44774 | B76: 0.44861111 | C76: 1297 | D76: 13002561 | E76: 13 | F76: 22589 | G76: Розничная реализация | H76: 15 | I76: 4735 | J76: ЮНИДОКС СОЛЮТАБ 100МГ. №10 ТАБ.ДИСПЕРГ. /АСТЕЛЛАС/ | K76: Пульс | L76: ЗиО ЗДОРОВЬЕ ЗАО | M76: 1 | N76: 311.78 | O76: 370 | P76: 0 | Q76: NULL | R76: NULL | S76: 29 | T76: 1 | U76: 6
A77: 44774 | B77: 0.44861111 | C77: 1297 | D77: 13002561 | E77: 13 | F77: 22589 | G77: Розничная реализация | H77: 15 | I77: 512333 | J77: ДЕЗЛОРАТАДИН-ВЕЛФАРМ 5МГ. №10 ТАБ. П/О | K77: ВИТТА КОМПАНИ ООО | L77: ВЕЛФАРМ ООО | M77: 1 | N77: 115.28 | O77: 158 | P77: 0 | Q77: NULL | R77: NULL | S77: 29 | T77: 1 | U77: 1
A78: 44774 | B78: 0.44861111 | C78: 1297 | D78: 13002561 | E78: 13 | F78: 22589 | G78: Розничная реализация | H78: 15 | I78: 292820 | J78: КАЛИНОВ РОДНИК ВОДА МИНЕР. 0,5Л. Н/ГАЗ. | K78: ПрофитМед | L78: ФОНТЕ-АКВА | M78: 1 | N78: 23.04 | O78: 38 | P78: 0 | Q78: NULL | R78: NULL | S78: 29 | T78: 1 | U78: 2
A79: 44774 | B79: 0.44861111 | C79: 1297 | D79: 13002561 | E79: 13 | F79: 22589 | G79: Розничная реализация | H79: 15 | I79: 1504331 | J79: Карта LOYALITY 0,01Р | K79: ООО "Континент" | L79: ФОНТЕ-АКВА | M79: 1 | N79: 0.01 | O79: 0.01 | P79: 0 | Q79: NULL | R79: NULL | S79: 29 | T79: 1 | U79: 3
A80: 44774 | B80: 0.48900463 | C80: 1312 | D80: 13002561 | E80: 13 | F80: 22589 | G80: Розничная реализация | H80: 18 | I80: 1504331 | J80: Карта LOYALITY 0,01Р | K80: ООО "Континент" | L80: ФОНТЕ-АКВА | M80: 1 | N80: 0.01 | O80: 0.01 | P80: 0 | Q80: NULL | R80: NULL | S80: 29 | T80: 1 | U80: 2
A81: 44774 | B81: 0.74574074 | C81: 1394 | D81: 13002561 | E81: 13 | F81: 22589 | G81: Розничная реализация | H81: 18 | I81: 1504331 | J81: Карта LOYALITY 0,01Р | K81: ООО "Континент" | L81: ФОНТЕ-АКВА | M81: 1 | N81: 0.01 | O81: 0.01 | P81: 0 | Q81: NULL | R81: NULL | S81: 29 | T81: 1 | U81: 1
A82: 44774 | B82: 0.45111111 | C82: 1298 | D82: 13002561 | E82: 13 | F82: 22589 | G82: Розничная реализация | H82: 18 | I82: 54354 | J82: АУГМЕНТИН 200МГ.+28,5МГ/5МЛ. 7,7Г. 70МЛ. ПОР. Д/СУСП. Д/ПРИЕМА ВНУТРЬ ФЛ. /ГЛАКСО/ | K82: Протек | L82: Глаксо Вэллком Продакшен | M82: 1 | N82: 134.66 | O82: 160 | P82: 0 | Q82: NULL | R82: NULL | S82: 29 | T82: 1 | U82: 1
A83: 44774 | B83: 0.45111111 | C83: 1298 | D83: 13002561 | E83: 13 | F83: 22589 | G83: Розничная реализация | H83: 18 | I83: 100086 | J83: ГЕКСОРАЛ ТАБС №20 ТАБ. Д/РАСС. | K83: Катрен г.Химки | L83: Зольдан Холдинг | M83: 1 | N83: 198.75 | O83: 249 | P83: 0 | Q83: NULL | R83: NULL | S83: 29 | T83: 1 | U83: 2
A84: 44774 | B84: 0.45111111 | C84: 1298 | D84: 13002561 | E84: 13 | F84: 22589 | G84: Розничная реализация | H84: 18 | I84: 46046 | J84: РОМАШКИ ЦВЕТКИ 1,5Г. №20 ПАК. /КРАСНОГОРСК/ | K84: Авеста | L84: КРАСНОГОРСКЛЕКСРЕДСТВА ОАО | M84: 1 | N84: 71.85 | O84: 103 | P84: 0 | Q84: NULL | R84: NULL | S84: 29 | T84: 1 | U84: 5
A85: 44774 | B85: 0.57680556 | C85: 1348 | D85: 13002561 | E85: 13 | F85: 22589 | G85: Розничная реализация | H85: 15 | I85: 46046 | J85: РОМАШКИ ЦВЕТКИ 1,5Г. №20 ПАК. /КРАСНОГОРСК/ | K85: Авеста | L85: КРАСНОГОРСКЛЕКСРЕДСТВА ОАО | M85: 1 | N85: 71.85 | O85: 103 | P85: 7 | Q85: 9 | R85: 200010021953 | S85: 29 | T85: 1 | U85: 6
A86: 44774 | B86: 0.45111111 | C86: 1298 | D86: 13002561 | E86: 13 | F86: 22589 | G86: Розничная реализация | H86: 18 | I86: 41241 | J86: НУРОФЕН 100МГ/5МЛ. 100МЛ. СУСП. КЛУБНИКА Д/ДЕТЕЙ ФЛ. /РЕКИТТ БЕНКИЗЕР/ | K86: Протек | L86: RECKITT BENCKISER S.A. | M86: 1 | N86: 99.97 | O86: 121.72 | P86: 0 | Q86: NULL | R86: NULL | S86: 29 | T86: 2 | U86: 3
A87: 44774 | B87: 0.45239583 | C87: 1299 | D87: 13002561 | E87: 13 | F87: 22589 | G87: Розничная реализация | H87: 18 | I87: 16407 | J87: РАСТОРОПША №100 ТАБ. | K87: Катрен г.Химки | L87: В-МИН ООО | M87: 1 | N87: 135.54 | O87: 211 | P87: 21 | Q87: 9 | R87: 200010023919 | S87: 29 | T87: 1 | U87: 4
A88: 44774 | B88: 0.45239583 | C88: 1299 | D88: 13002561 | E88: 13 | F88: 22589 | G88: Розничная реализация | H88: 18 | I88: 26351 | J88: 911-ВЕНОЛГОН ГЕЛЬ Д/НОГ ПРИ ТЯЖЕСТИ,БОЛИ,ОТЕКАХ 100МЛ. ТУБА | K88: Протек | L88: ТВИНС ТЭК | M88: 1 | N88: 75.81 | O88: 120 | P88: 12 | Q88: 9 | R88: 200010023919 | S88: 29 | T88: 1 | U88: 1
A89: 44774 | B89: 0.45239583 | C89: 1299 | D89: 13002561 | E89: 13 | F89: 22589 | G89: Розничная реализация | H89: 18 | I89: 22533 | J89: КОНКОР КОР 2,5МГ. №30 ТАБ. П/П/О /МЕРК/ | K89: ГРАНД КАПИТАЛ СМОЛЕНСК ООО ФК | L89: НАНОЛЕК | M89: 1 | N89: 130.83 | O89: 151 | P89: 7 | Q89: 9 | R89: 200010023919 | S89: 29 | T89: 1 | U89: 3
A90: 44774 | B90: 0.66700231 | C90: 1370 | D90: 13002561 | E90: 13 | F90: 22589 | G90: Розничная реализация | H90: 18 | I90: 22533 | J90: КОНКОР КОР 2,5МГ. №30 ТАБ. П/П/О /МЕРК/ | K90: ГРАНД КАПИТАЛ СМОЛЕНСК ООО ФК | L90: НАНОЛЕК | M90: 1 | N90: 130.83 | O90: 151 | P90: 7 | Q90: 9 | R90: 200010016459 | S90: 29 | T90: 1 | U90: 2
A91: 44774 | B91: 0.45239583 | C91: 1299 | D91: 13002561 | E91: 13 | F91: 22589 | G91: Розничная реализация | H91: 18 | I91: 488299 | J91: БИСОПРОЛОЛ 2,5МГ. №60 ТАБ. П/О /ВЕРТЕКС/ | K91: Пульс | L91: ВЕРТЕКС | M91: 1 | N91: 156.2 | O91: 186 | P91: 9 | Q91: 9 | R91: 200010023919 | S91: 29 | T91: 1 | U91: 2
A92: 44774 | B92: 0.45282407 | C92: 1300 | D92: 13002561 | E92: 13 | F92: 22589 | G92: Розничная реализация | H92: 18 | I92: 72392 | J92: СНУП 0,1% 90МКГ/ДОЗА 15МЛ. НАЗАЛ.СПРЕЙ ФЛ. /ШТАДА/ | K92: Катрен г.Химки | L92: ХЕМОМОНТ | M92: 1 | N92: 103.5 | O92: 122 | P92: 6 | Q92: 9 | R92: 200010018337 | S92: 29 | T92: 1 | U92: 1
A93: 44774 | B93: 0.81680556 | C93: 1410 | D93: 13002561 | E93: 13 | F93: 22589 | G93: Розничная реализация | H93: 18 | I93: 72392 | J93: СНУП 0,1% 90МКГ/ДОЗА 15МЛ. НАЗАЛ.СПРЕЙ ФЛ. /ШТАДА/ | K93: Катрен г.Химки | L93: ХЕМОМОНТ | M93: 1 | N93: 103.5 | O93: 122 | P93: 6 | Q93: 9 | R93: 200010015192 | S93: 29 | T93: 1 | U93: 2
A94: 44774 | B94: 0.46287037 | C94: 1301 | D94: 13002561 | E94: 13 | F94: 22589 | G94: Розничная реализация | H94: 18 | I94: 17182 | J94: ПОЛИДЕКСА С ФЕНИЛЭФРИНОМ 15МЛ. НАЗАЛ.СПРЕЙ ФЛ. | K94: Здравсервис | L94: LABORATORIES DU DOCTEUR EMILE BOUCHARA | M94: 1 | N94: 525 | O94: 678 | P94: 20.21 | Q94: 925 | R94: 200000000492 | S94: 29 | T94: 1 | U94: 1
A95: 44774 | B95: 0.46287037 | C95: 1301 | D95: 13002561 | E95: 13 | F95: 22589 | G95: Розничная реализация | H95: 18 | I95: 26900 | J95: РЕГЕЦИН 15Г. ГЕЛЬ П/УГРЕВОЙ СЫПИ | K95: Здравсервис | L95: ДИОНИС ООО | M95: 1 | N95: 190 | O95: 295 | P95: 8.79 | Q95: 925 | R95: 200000000492 | S95: 29 | T95: 1 | U95: 2
A96: 44774 | B96: 0.46440972 | C96: 1302 | D96: 13002561 | E96: 13 | F96: 22589 | G96: Розничная реализация | H96: 15 | I96: 30028 | J96: ГЕМАТОГЕН РУССКИЙ ДЕТСКИЙ 40Г. ПЛИТКА /ФАРМ-ПРО/ | K96: Катрен г.Химки | L96: ФАРМ-ПРО | M96: 2 | N96: 10.01 | O96: 17 | P96: 3 | Q96: 9 | R96: 200010019633 | S96: 29 | T96: 1 | U96: 1
A97: 44774 | B97: 0.60392361 | C97: 1356 | D97: 13002561 | E97: 13 | F97: 22589 | G97: Розничная реализация | H97: 18 | I97: 30028 | J97: ГЕМАТОГЕН РУССКИЙ ДЕТСКИЙ 40Г. ПЛИТКА /ФАРМ-ПРО/ | K97: Катрен г.Химки | L97: ФАРМ-ПРО | M97: 1 | N97: 10.01 | O97: 17 | P97: 0 | Q97: NULL | R97: NULL | S97: 29 | T97: 1 | U97: 1
A98: 44774 | B98: 0.46513889 | C98: 1303 | D98: 13002561 | E98: 13 | F98: 22589 | G98: Розничная реализация | H98: 15 | I98: 371526 | J98: ТИАМИНА ХЛОРИД 50МГ/МЛ. 1МЛ. №10 Р-Р Д/В/М ВВЕД. АМП. (ВИТАМИН В1) /СТАТУСФАРМ/ЕРЕВАН.ФФ/ | K98: Пульс | L98: СТАТУСФАРМ ООО | M98: 1 | N98: 27.12 | O98: 33 | P98: 1 | Q98: 9 | R98: 200010000167 | S98: 29 | T98: 1 | U98: 1
A99: 44774 | B99: 0.46513889 | C99: 1303 | D99: 13002561 | E99: 13 | F99: 22589 | G99: Розничная реализация | H99: 15 | I99: 371526 | J99: ТИАМИНА ХЛОРИД 50МГ/МЛ. 1МЛ. №10 Р-Р Д/В/М ВВЕД. АМП. (ВИТАМИН В1) /СТАТУСФАРМ/ЕРЕВАН.ФФ/ | K99: ВИТТА КОМПАНИ ООО | L99: СТАТУСФАРМ ООО | M99: 1 | N99: 27.06 | O99: 33.54 | P99: 1.54 | Q99: 9 | R99: 200010000167 | S99: 29 | T99: 1 | U99: 2
A100: 44774 | B100: 0.46856481 | C100: 1304 | D100: 13002561 | E100: 13 | F100: 22589 | G100: Розничная реализация | H100: 15 | I100: 79666 | J100: АРКОКСИА 90МГ. №28 ТАБ. П/П/О | K100: Катрен г.Химки | L100: РОВИ КОНТРАКТ | M100: 1 | N100: 1380.93 | O100: 1727 | P100: 120 | Q100: 9 | R100: 200010026858 | S100: 29 | T100: 1 | U100: 1
...

Sheet КОЛИЧЕСТВО
A3: Названия строк | B3: Сумма по столбцу DR_Kol | D3: Названия | E3: Сумма по столбцу DR_Kol | F3: Доля | G3: Накопит. | H3: КОЛ | I3: СУМ ПРОД | J3: МЕСЯЧ. Рент
A4: 911-ВЕНОЛГОН ГЕЛЬ Д/НОГ ПРИ ТЯЖЕСТИ,БОЛИ,ОТЕКАХ 100МЛ. ТУБА | B4: 1 | D4: ЛЕЙКОПЛАСТЫРЬ БАКТЕР. 2,5Х7,2 №1 /ВЕРОФАРМ/ | E4: 68 | F4: =E4/SUM($E$4:$E$806) -> 0.042265927 | G4: =F4 -> 0.042265927 | H4: =IF(G4<0.8, "A", IF(G4<0.95, "B","C")) -> A | I4: =VLOOKUP(D4,'СУММА ПРОДАЖ'!J:N, 5, FALSE) -> B | J4: =VLOOKUP(D4, 'МЕСЯЧНАЯ ОБОР.'!$V$4:$W$806, 2, FALSE) -> A
A5: 911-ГЕЛЬ-БАЛЬЗАМ Д/НОГ КОНСКИЙ КАШТАН 100МЛ. ТУБА | B5: 1 | D5: НАФТИЗИН 0,1% 15МЛ. НАЗАЛ.КАПЛИ ФЛ./КАП. /СЛАВЯНСКАЯ АПТЕКА/ | E5: 35 | F5: =E5/SUM($E$4:$E$806) -> 0.021754521 | G5: =F5+G4 -> 0.064020449 | H5: =IF(G5<0.8, "A", IF(G5<0.95, "B","C")) -> A | I5: =VLOOKUP(D5,'СУММА ПРОДАЖ'!J:N, 5, FALSE) -> B | J5: =VLOOKUP(D5, 'МЕСЯЧНАЯ ОБОР.'!$V$4:$W$806, 2, FALSE) -> A
A6: 911-ГЕЛЬ-БАЛЬЗАМ Д/СУСТАВОВ РАЗОГР. ОКОПНИК+МУРАВ.К-ТА 100МЛ. | B6: 1 | D6: ПАКЕТ | E6: 26 | F6: =E6/SUM($E$4:$E$806) -> 0.016160502 | G6: =F6+G5 -> 0.08018095 | H6: =IF(G6<0.8, "A", IF(G6<0.95, "B","C")) -> A | I6: =VLOOKUP(D6,'СУММА ПРОДАЖ'!J:N, 5, FALSE) -> C | J6: =VLOOKUP(D6, 'МЕСЯЧНАЯ ОБОР.'!$V$4:$W$806, 2, FALSE) -> A
A7: L-ТИРОКСИН 100МКГ. №100 ТАБ. /БЕРЛИН ХЕМИ/ | B7: 1 | D7: ВАЛИДОЛ 60МГ. №10 ТАБ. ПОДЪЯЗЫЧ. /ФАРМСТАНДАРТ/ | E7: 25 | F7: =E7/SUM($E$4:$E$806) -> 0.015538944 | G7: =F7+G6 -> 0.095719894 | H7: =IF(G7<0.8, "A", IF(G7<0.95, "B","C")) -> A | I7: =VLOOKUP(D7,'СУММА ПРОДАЖ'!J:N, 5, FALSE) -> A | J7: =VLOOKUP(D7, 'МЕСЯЧНАЯ ОБОР.'!$V$4:$W$806, 2, FALSE) -> A
A8: L-ТИРОКСИН 150МКГ. №100 ТАБ. /БЕРЛИН ХЕМИ/ | B8: 1 | D8: БОРНАЯ К-ТА 10Г. ДЕЗ.СР-ВО ПОР. (НДС 20%) | E8: 22 | F8: =E8/SUM($E$4:$E$806) -> 0.013674271 | G8: =F8+G7 -> 0.10939416 | H8: =IF(G8<0.8, "A", IF(G8<0.95, "B","C")) -> A | I8: =VLOOKUP(D8,'СУММА ПРОДАЖ'!J:N, 5, FALSE) -> B | J8: =VLOOKUP(D8, 'МЕСЯЧНАЯ ОБОР.'!$V$4:$W$806, 2, FALSE) -> A
A9: L-ТИРОКСИН 50МКГ. №50 ТАБ. /БЕРЛИН ХЕМИ/ | B9: 2 | D9: ГЕМАТОГЕН РУССКИЙ ДЕТСКИЙ 40Г. ПЛИТКА /ФАРМ-ПРО/ | E9: 17 | F9: =E9/SUM($E$4:$E$806) -> 0.010566482 | G9: =F9+G8 -> 0.11996065 | H9: =IF(G9<0.8, "A", IF(G9<0.95, "B","C")) -> A | I9: =VLOOKUP(D9,'СУММА ПРОДАЖ'!J:N, 5, FALSE) -> B | J9: =VLOOKUP(D9, 'МЕСЯЧНАЯ ОБОР.'!$V$4:$W$806, 2, FALSE) -> A
A10: L-ТИРОКСИН 75МКГ. №100 ТАБ. /БЕРЛИН ХЕМИ/ | B10: 3 | D10: КОРВАЛОЛ 25МЛ. КАПЛИ Д/ПРИЕМА ВНУТРЬ ФЛ. И/У /ФАРМСТАНДАРТ ЛЕКСРЕДСТВА/ | E10: 14 | F10: =E10/SUM($E$4:$E$806) -> 0.0087018086 | G10: =F10+G9 -> 0.12866246 | H10: =IF(G10<0.8, "A", IF(G10<0.95, "B","C")) -> A | I10: =VLOOKUP(D10,'СУММА ПРОДАЖ'!J:N, 5, FALSE) -> A | J10: =VLOOKUP(D10, 'МЕСЯЧНАЯ ОБОР.'!$V$4:$W$806, 2, FALSE) -> A
A11: NF ВАТА ХИРУРГ. СТЕР. 100Г. /НЬЮФАРМ/ | B11: 1 | D11: ЛЕЙКОПЛАСТЫРЬ БАКТЕР. 4Х10 №1 /ВЕРОФАРМ/ | E11: 14 | F11: =E11/SUM($E$4:$E$806) -> 0.0087018086 | G11: =F11+G10 -> 0.13736426 | H11: =IF(G11<0.8, "A", IF(G11<0.95, "B","C")) -> A | I11: =VLOOKUP(D11,'СУММА ПРОДАЖ'!J:N, 5, FALSE) -> C | J11: =VLOOKUP(D11, 'МЕСЯЧНАЯ ОБОР.'!$V$4:$W$806, 2, FALSE) -> A
A12: АДЖИСЕПТ МЕД+ЛИМОН №24 ТАБ. Д/РАСС. | B12: 1 | D12: ЛЕЙКОПЛАСТЫРЬ БАКТЕР. 6X10 №1 /ВЕРОФАРМ/ | E12: 13 | F12: =E12/SUM($E$4:$E$806) -> 0.0080802508 | G12: =F12+G11 -> 0.14544451 | H12: =IF(G12<0.8, "A", IF(G12<0.95, "B","C")) -> A | I12: =VLOOKUP(D12,'СУММА ПРОДАЖ'!J:N, 5, FALSE) -> C | J12: =VLOOKUP(D12, 'МЕСЯЧНАЯ ОБОР.'!$V$4:$W$806, 2, FALSE) -> A
A13: АДЖИСЕПТ МЕНТОЛ+ЭВКАЛИПТ №24 ТАБ. Д/РАСС. | B13: 1 | D13: МЕНОВАЗИН 40МЛ. №1 СПИРТ. Р-Р Д/НАРУЖ.ПРИМ. ФЛ. /САМАРАМЕДПРОМ/ | E13: 13 | F13: =E13/SUM($E$4:$E$806) -> 0.0080802508 | G13: =F13+G12 -> 0.15352477 | H13: =IF(G13<0.8, "A", IF(G13<0.95, "B","C")) -> A | I13: =VLOOKUP(D13,'СУММА ПРОДАЖ'!J:N, 5, FALSE) -> A | J13: =VLOOKUP(D13, 'МЕСЯЧНАЯ ОБОР.'!$V$4:$W$806, 2, FALSE) -> A
A14: АЕВИТ 200МГ. №20 КАПС. (БАД) /МЕЛИГЕН/ | B14: 1 | D14: ПЕРЕКИСЬ ВОДОРОДА 3% 100МЛ. №1 Р-Р ДЕЗ.СР-ВО ФЛ. (НДС 20%) | E14: 13 | F14: =E14/SUM($E$4:$E$806) -> 0.0080802508 | G14: =F14+G13 -> 0.16160502 | H14: =IF(G14<0.8, "A", IF(G14<0.95, "B","C")) -> A | I14: =VLOOKUP(D14,'СУММА ПРОДАЖ'!J:N, 5, FALSE) -> B | J14: =VLOOKUP(D14, 'МЕСЯЧНАЯ ОБОР.'!$V$4:$W$806, 2, FALSE) -> A
A15: АЗАРГА 10МГ/МЛ.+5МГ/МЛ. 5МЛ. №1 ГЛ.КАПЛИ ФЛ./КАП. | B15: 2 | D15: РАУНАТИН 2МГ. №50 ТАБ. П/О /ЗДОРОВЬЕ/ | E15: 13 | F15: =E15/SUM($E$4:$E$806) -> 0.0080802508 | G15: =F15+G14 -> 0.16968527 | H15: =IF(G15<0.8, "A", IF(G15<0.95, "B","C")) -> A | I15: =VLOOKUP(D15,'СУММА ПРОДАЖ'!J:N, 5, FALSE) -> A | J15: =VLOOKUP(D15, 'МЕСЯЧНАЯ ОБОР.'!$V$4:$W$806, 2, FALSE) -> A
A16: АЗИТРОМИЦИН 500МГ. №3 КАПС. /ПРОИЗВОДСТВО МЕДИКАМЕНТОВ/ ПроМед/ | B16: 2 | D16: Карта LOYALITY 0,01Р | E16: 12 | F16: =E16/SUM($E$4:$E$806) -> 0.007458693 | G16: =F16+G15 -> 0.17714396 | H16: =IF(G16<0.8, "A", IF(G16<0.95, "B","C")) -> A | I16: =VLOOKUP(D16,'СУММА ПРОДАЖ'!J:N, 5, FALSE) -> C | J16: =VLOOKUP(D16, 'МЕСЯЧНАЯ ОБОР.'!$V$4:$W$806, 2, FALSE) -> A
... A806: ЮНИДОКС СОЛЮТАБ 100МГ. №20 ТАБ.ДИСПЕРГ. /АСТЕЛЛАС/ | B806: 1 | D806: ХАРТМАНН КОСМОПОР Е ПОВЯЗКА 7,2Х5СМ №50 П/ОПЕР. САМОКЛ. СТЕР. /АРТ.9008705/ [HARTMANN COSMOPOR] | E806: 0.04 | F806: =E806/SUM($E$4:$E$806) -> 2.486231e-05 | G806: =F806+G805 -> 1 | H806: =IF(G806<0.8, "A", IF(G806<0.95, "B","C")) -> C | I806: =VLOOKUP(D806,'СУММА ПРОДАЖ'!J:N, 5, FALSE) -> C | J806: =VLOOKUP(D806, 'МЕСЯЧНАЯ ОБОР.'!$V$4:$W$806, 2, FALSE) -> C
A807: Общий итог | B807: 1608.861

Sheet СУММА ПРОДАЖ
A1: DR_NDrugs | B1: DR_Croz (розничная цена) | C1: DR_Kol | D1: DR_Sdisc (сумма скидки) | E1: Сумма продаж | G1: Названия строк | H1: Сумма по столбцу Сумма продаж | J1: Названия строк | K1: Сумма по столбцу Сумма продаж | L1: Доля | M1: Накоп. Доля
A2: ГАСТАЛ №12 ТАБ. Д/РАСС. | B2: 270 | C2: 1 | D2: 0 | E2: =C2*B2-D2 -> 270 | G2: 911-ВЕНОЛГОН ГЕЛЬ Д/НОГ ПРИ ТЯЖЕСТИ,БОЛИ,ОТЕКАХ 100МЛ. ТУБА | H2: 120 | J2: ДЕТРАЛЕКС 1000МГ. №60 ТАБ. П/П/О | K2: 11948 | L2: =K2/SUM($K$2:$K$804) -> 0.032459264 | M2: =L2 -> 0.032459264 | N2: =IF(M2<0.8, "A", IF(M2<0.95,"B","C")) -> A
A3: ТОБРОПТ 0,3% 5МЛ. №1 ГЛ.КАПЛИ ФЛ./КАП. /РОМФАРМ/ | B3: 127 | C3: 1 | D3: 6 | E3: =C3*B3-D3 -> 121 | G3: 911-ГЕЛЬ-БАЛЬЗАМ Д/НОГ КОНСКИЙ КАШТАН 100МЛ. ТУБА | H3: 105 | J3: ЭЛИКВИС 5МГ. №60 ТАБ. П/П/О /ПФАЙЗЕР/БРИСТОЛ-МАЙЕРС/ | K3: 5126 | L3: =K3/SUM($K$2:$K$804) -> 0.013925861 | M3: =L3+M2 -> 0.046385126 | N3: =IF(M3<0.8, "A", IF(M3<0.95,"B","C")) -> A
A4: ЭЛИКВИС 5МГ. №60 ТАБ. П/П/О /ПФАЙЗЕР/БРИСТОЛ-МАЙЕРС/ | B4: 2563 | C4: 1 | D4: 76 | E4: =C4*B4-D4 -> 2487 | G4: 911-ГЕЛЬ-БАЛЬЗАМ Д/СУСТАВОВ РАЗОГР. ОКОПНИК+МУРАВ.К-ТА 100МЛ. | H4: 122 | J4: ГЕЛАДРИНК ФОРТЕ ПОР. Д/ПРИЕМА ВНУТРЬ АПЕЛЬСИН 420Г. БАНКА | K4: 4985 | L4: =K4/SUM($K$2:$K$804) -> 0.013542805 | M4: =L4+M3 -> 0.05992793 | N4: =IF(M4<0.8, "A", IF(M4<0.95,"B","C")) -> A
A5: АРБИДОЛ МАКСИМУМ 200МГ. №10 КАПС. /ОТИСИФАРМ/ФАРМСТАНДАРТ/ | B5: 541 | C5: 1 | D5: 0 | E5: =C5*B5-D5 -> 541 | G5: L-ТИРОКСИН 100МКГ. №100 ТАБ. /БЕРЛИН ХЕМИ/ | H5: 153 | J5: ОМРОН ТОНОМЕТР M2 БАЗИК АВТОМАТ АДАПТЕР /АРТ.HEM-7121-ARU/ [OMRON] | K5: 3832 | L5: =K5/SUM($K$2:$K$804) -> 0.010410437 | M5: =L5+M4 -> 0.070338367 | N5: =IF(M5<0.8, "A", IF(M5<0.95,"B","C")) -> A
A6: ЭНАМ 2,5МГ. №20 ТАБ. /Д-Р РЕДДИ/ | B6: 22 | C6: 1 | D6: 1 | E6: =C6*B6-D6 -> 21 | G6: L-ТИРОКСИН 150МКГ. №100 ТАБ. /БЕРЛИН ХЕМИ/ | H6: 177 | J6: ИНЪЕКТРАН 100МГ/МЛ. 2МЛ. №10 Р-Р Д/В/М АМП. | K6: 3697 | L6: =K6/SUM($K$2:$K$804) -> 0.010043681 | M6: =L6+M5 -> 0.080382048 | N6: =IF(M6<0.8, "A", IF(M6<0.95,"B","C")) -> A
A7: ЭНАМ 2,5МГ. №20 ТАБ. /Д-Р РЕДДИ/ | B7: 22 | C7: 1 | D7: 1 | E7: =C7*B7-D7 -> 21 | G7: L-ТИРОКСИН 50МКГ. №50 ТАБ. /БЕРЛИН ХЕМИ/ | H7: 199 | J7: ЛИТТЛ ДОКТОР ТОНОМЕТР LD-51U АВТОМАТ НА ПЛЕЧО 22-42СМ. +АДАПТЕР [LITTLE DOCTOR] | K7: 3497 | L7: =K7/SUM($K$2:$K$804) -> 0.0095003388 | M7: =L7+M6 -> 0.089882387 | N7: =IF(M7<0.8, "A", IF(M7<0.95,"B","C")) -> A
A8: КЛОПИДОГРЕЛ-СЗ 75МГ. №28 ТАБ. П/П/О /СЕВЕРНАЯ ЗВЕЗДА/ | B8: 475 | C8: 1 | D8: 23 | E8: =C8*B8-D8 -> 452 | G8: L-ТИРОКСИН 75МКГ. №100 ТАБ. /БЕРЛИН ХЕМИ/ | H8: 432 | J8: ВЕССЕЛ ДУЭ Ф 250ЕД №60 КАПС. | K8: 3482 | L8: =K8/SUM($K$2:$K$804) -> 0.0094595881 | M8: =L8+M7 -> 0.099341975 | N8: =IF(M8<0.8, "A", IF(M8<0.95,"B","C")) -> A
A9: КО-ВАМЛОСЕТ 5МГ.+160МГ.+12,5МГ. №30 ТАБ. П/П/О | B9: 693 | C9: 1 | D9: 48 | E9: =C9*B9-D9 -> 645 | G9: NF ВАТА ХИРУРГ. СТЕР. 100Г. /НЬЮФАРМ/ | H9: 71 | J9: ПРАДАКСА 110МГ. №180 КАПС. /БЕРИНГЕР/ | K9: 3458.3333 | L9: =K9/SUM($K$2:$K$804) -> 0.0093952925 | M9: =L9+M8 -> 0.10873727 | N9: =IF(M9<0.8, "A", IF(M9<0.95,"B","C")) -> A
A10: АТОРВАСТАТИН-СЗ 20МГ. №60 ТАБ. П/П/О /СЕВЕРНАЯ ЗВЕЗДА/ | B10: 418 | C10: 1 | D10: 20 | E10: =C10*B10-D10 -> 398 | G10: АДЖИСЕПТ МЕД+ЛИМОН №24 ТАБ. Д/РАСС. | H10: 213 | J10: ДЮФАЛАК 667МГ/МЛ. 1000МЛ. СИРОП ФЛ. +МЕРН.СТАКАН /ЭББОТТ/СОЛВЕЙ/ | K10: 2703.89 | L10: =K10/SUM($K$2:$K$804) -> 0.007345688 | M10: =L10+M9 -> 0.11608296 | N10: =IF(M10<0.8, "A", IF(M10<0.95,"B","C")) -> A
A11: АТОРВАСТАТИН-СЗ 40МГ. №30 ТАБ. П/П/О /СЕВЕРНАЯ ЗВЕЗДА/ | B11: 340 | C11: 1 | D11: 17 | E11: =C11*B11-D11 -> 323 | G11: АДЖИСЕПТ МЕНТОЛ+ЭВКАЛИПТ №24 ТАБ. Д/РАСС. | H11: 216 | J11: ЛОНГИДАЗА 3000МЕ №10 СУПП. РЕКТ./ВАГИН. | K11: 2642 | L11: =K11/SUM($K$2:$K$804) -> 0.0071775508 | M11: =L11+M10 -> 0.12326051 | N11: =IF(M11<0.8, "A", IF(M11<0.95,"B","C")) -> A
A12: КСИМЕЛИН ЭКСТРА 84МКГ/ДОЗА+70МКГ/ДОЗА 10МЛ. №1 НАЗАЛ.СПРЕЙ ДОЗИР. ФЛ. | B12: 284 | C12: 1 | D12: 0 | E12: =C12*B12-D12 -> 284 | G12: АЕВИТ 200МГ. №20 КАПС. (БАД) /МЕЛИГЕН/ | H12: 49 | J12: АЗАРГА 10МГ/МЛ.+5МГ/МЛ. 5МЛ. №1 ГЛ.КАПЛИ ФЛ./КАП. | K12: 2628 | L12: =K12/SUM($K$2:$K$804) -> 0.0071395168 | M12: =L12+M11 -> 0.13040002 | N12: =IF(M12<0.8, "A", IF(M12<0.95,"B","C")) -> A
A13: NF ВАТА ХИРУРГ. СТЕР. 100Г. /НЬЮФАРМ/ | B13: 71 | C13: 1 | D13: 7 | E13: =C13*B13-D13 -> 64 | G13: АЗАРГА 10МГ/МЛ.+5МГ/МЛ. 5МЛ. №1 ГЛ.КАПЛИ ФЛ./КАП. | H13: 2628 | J13: ВИТАПРОСТ 10МГ. №10 СУПП. РЕКТ. /НИЖФАРМ/ | K13: 2596 | L13: =K13/SUM($K$2:$K$804) -> 0.007052582 | M13: =L13+M12 -> 0.13745261 | N13: =IF(M13<0.8, "A", IF(M13<0.95,"B","C")) -> A
A14: СТОПСЕПТ ПЛЮС 90% 100МЛ. ДЕЗ.СР-ВО ФЛ. | B14: 58 | C14: 1 | D14: 5 | E14: =C14*B14-D14 -> 53 | G14: АЗИТРОМИЦИН 500МГ. №3 КАПС. /ПРОИЗВОДСТВО МЕДИКАМЕНТОВ/ ПроМед/ | H14: 168 | J14: ТОНОМЕТР UA-604 П/АВТОМАТ [AND] | K14: 2456 | L14: =K14/SUM($K$2:$K$804) -> 0.0066722425 | M14: =L14+M13 -> 0.14412485 | N14: =IF(M14<0.8, "A", IF(M14<0.95,"B","C")) -> A
... A804: КОРВАЛОЛ 25МЛ. КАПЛИ Д/ПРИЕМА ВНУТРЬ ФЛ. И/У /ФАРМСТАНДАРТ ЛЕКСРЕДСТВА/ | B804: 26 | C804: 1 | D804: 1 | E804: =C804*B804-D804 -> 25 | G804: ЮНИДОКС СОЛЮТАБ 100МГ. №20 ТАБ.ДИСПЕРГ. /АСТЕЛЛАС/ | H804: 658 | J804: Карта LOYALITY 0,01Р | K804: 0.12 | L804: =K804/SUM($K$2:$K$804) -> 3.2600533e-07 | M804: =L804+M803 -> 1 | N804: =IF(M804<0.8, "A", IF(M804<0.95,"B","C")) -> C
A805: КОРВАЛОЛ 25МЛ. КАПЛИ Д/ПРИЕМА ВНУТРЬ ФЛ. И/У /ФАРМСТАНДАРТ ЛЕКСРЕДСТВА/ | B805: 26 | C805: 1 | D805: 1 | E805: =C805*B805-D805 -> 25 | G805: Общий итог | H805: 368092.14
A806: КОРВАЛОЛ 25МЛ. КАПЛИ Д/ПРИЕМА ВНУТРЬ ФЛ. И/У /ФАРМСТАНДАРТ ЛЕКСРЕДСТВА/ | B806: 26 | C806: 1 | D806: 1 | E806: =C806*B806-D806 -> 25
A807: КОРВАЛОЛ 25МЛ. КАПЛИ Д/ПРИЕМА ВНУТРЬ ФЛ. И/У /ФАРМСТАНДАРТ ЛЕКСРЕДСТВА/ | B807: 26 | C807: 1 | D807: 1 | E807: =C807*B807-D807 -> 25
A808: ГЛИЦИН 100МГ. №100 ТАБ. ПОДЪЯЗЫЧ. /БИОТИКИ/ | B808: 70 | C808: 1 | D808: 3 | E808: =C808*B808-D808 -> 67
A809: ГИПОСАРТ 16МГ. №28 ТАБ. | B809: 493 | C809: 1 | D809: 0 | E809: =C809*B809-D809 -> 493
A810: МЕКСИДОЛ 125МГ. №50 ТАБ. П/П/О /ФАРМАСОФТ/ЗИО ЗДОРОВЬЕ/ | B810: 490 | C810: 1 | D810: 0 | E810: =C810*B810-D810 -> 490
A811: МЕКСИДОЛ 125МГ. №50 ТАБ. П/П/О /ФАРМАСОФТ/ЗИО ЗДОРОВЬЕ/ | B811: 490 | C811: 1 | D811: 0 | E811: =C811*B811-D811 -> 490
A812: НЕО-АНГИН №24 ТАБ. Д/РАСС. САХ. | B812: 217 | C812: 1 | D812: 0 | E812: =C812*B812-D812 -> 217
A813: Д.ТАЙСС АНГИ СЕПТ МЕД+ЛИПА №24 ТАБ. Д/РАСС. | B813: 222 | C813: 1 | D813: 0 | E813: =C813*B813-D813 -> 222
A814: ФЕРРОГЕМАТОГЕН 50Г. ПАСТИЛКА ЖЕВ. (ПЛИТКА) | B814: 30 | C814: 2 | D814: 6 | E814: =C814*B814-D814 -> 54
A815: ФЕРРОГЕМАТОГЕН 50Г. ПАСТИЛКА ЖЕВ. (ПЛИТКА) | B815: 30 | C815: 1 | D815: 3 | E815: =C815*B815-D815 -> 27
A816: АСКОРБИНКА ЛУНТИК ВИТ.С №10 ТАБ. (30Г.) /ФАРМ-ПРО/ТИГОДА-ФАРМ/ | B816: 16 | C816: 1 | D816: 0 | E816: =C816*B816-D816 -> 16
A817: АСКОРБИНОВАЯ К-ТА 25МГ. ВИШНЯ №10 ТАБ. КРУТКА САХ. /АСКОПРОМ/ | B817: 11 | C817: 1 | D817: 0 | E817: =C817*B817-D817 -> 11
... A1449: ГЕМАТОГЕН РУССКИЙ КЕДРОВЫЙ ОРЕХ 40Г. ПЛИТКА /ФАРМ-ПРО/ | B1449: 30 | C1449: 1 | D1449: 3 | E1449: =C1449*B1449-D1449 -> 27

Sheet МЕСЯЧНАЯ ОБОР.
A1: DR_Dat | B1: DR_NDrugs | C1: DR_Kol
A2: 44774 | B2: ГАСТАЛ №12 ТАБ. Д/РАСС. | C2: 1 | F2: Сумма по столбцу DR_Kol | G2: Названия столбцов
A3: 44774 | B3: ТОБРОПТ 0,3% 5МЛ. №1 ГЛ.КАПЛИ ФЛ./КАП. /РОМФАРМ/ | C3: 1 | G3: 44774 | H3: 44775 | I3: 44776 | J3: 44777 | K3: 44778 | L3: Общий итог | P3: Общий итог | Q3: Месяч. Обор
A4: 44774 | B4: ЭЛИКВИС 5МГ. №60 ТАБ. П/П/О /ПФАЙЗЕР/БРИСТОЛ-МАЙЕРС/ | C4: 1 | F4: 911-ВЕНОЛГОН ГЕЛЬ Д/НОГ ПРИ ТЯЖЕСТИ,БОЛИ,ОТЕКАХ 100МЛ. ТУБА | G4: 1 | L4: 1 | O4: ЛЕЙКОПЛАСТЫРЬ БАКТЕР. 2,5Х7,2 №1 /ВЕРОФАРМ/ | P4: 68 | Q4: =(P4/5)*30 -> 408 | R4: =Q4/SUM($Q$4:$Q$806) -> 0.042265927 | S4: =R4 -> 0.042265927 | T4: =IF(S4<0.8,"A", IF(S4<0.95,"B","C")) -> A | V4: ЛЕЙКОПЛАСТЫРЬ БАКТЕР. 2,5Х7,2 №1 /ВЕРОФАРМ/ | W4: A
A5: 44774 | B5: АРБИДОЛ МАКСИМУМ 200МГ. №10 КАПС. /ОТИСИФАРМ/ФАРМСТАНДАРТ/ | C5: 1 | F5: 911-ГЕЛЬ-БАЛЬЗАМ Д/НОГ КОНСКИЙ КАШТАН 100МЛ. ТУБА | H5: 1 | L5: 1 | O5: НАФТИЗИН 0,1% 15МЛ. НАЗАЛ.КАПЛИ ФЛ./КАП. /СЛАВЯНСКАЯ АПТЕКА/ | P5: 35 | Q5: =(P5/5)*30 -> 210 | R5: =Q5/SUM($Q$4:$Q$806) -> 0.021754521 | S5: =R5+S4 -> 0.064020449 | T5: =IF(S5<0.8,"A", IF(S5<0.95,"B","C")) -> A | V5: НАФТИЗИН 0,1% 15МЛ. НАЗАЛ.КАПЛИ ФЛ./КАП. /СЛАВЯНСКАЯ АПТЕКА/ | W5: A
A6: 44774 | B6: ЭНАМ 2,5МГ. №20 ТАБ. /Д-Р РЕДДИ/ | C6: 1 | F6: 911-ГЕЛЬ-БАЛЬЗАМ Д/СУСТАВОВ РАЗОГР. ОКОПНИК+МУРАВ.К-ТА 100МЛ. | I6: 1 | L6: 1 | O6: ПАКЕТ | P6: 26 | Q6: =(P6/5)*30 -> 156 | R6: =Q6/SUM($Q$4:$Q$806) -> 0.016160502 | S6: =R6+S5 -> 0.08018095 | T6: =IF(S6<0.8,"A", IF(S6<0.95,"B","C")) -> A | V6: ПАКЕТ | W6: A
A7: 44774 | B7: ЭНАМ 2,5МГ. №20 ТАБ. /Д-Р РЕДДИ/ | C7: 1 | F7: L-ТИРОКСИН 100МКГ. №100 ТАБ. /БЕРЛИН ХЕМИ/ | G7: 1 | L7: 1 | O7: ВАЛИДОЛ 60МГ. №10 ТАБ. ПОДЪЯЗЫЧ. /ФАРМСТАНДАРТ/ | P7: 25 | Q7: =(P7/5)*30 -> 150 | R7: =Q7/SUM($Q$4:$Q$806) -> 0.015538944 | S7: =R7+S6 -> 0.095719894 | T7: =IF(S7<0.8,"A", IF(S7<0.95,"B","C")) -> A | V7: ВАЛИДОЛ 60МГ. №10 ТАБ. ПОДЪЯЗЫЧ. /ФАРМСТАНДАРТ/ | W7: A
A8: 44774 | B8: КЛОПИДОГРЕЛ-СЗ 75МГ. №28 ТАБ. П/П/О /СЕВЕРНАЯ ЗВЕЗДА/ | C8: 1 | F8: L-ТИРОКСИН 150МКГ. №100 ТАБ. /БЕРЛИН ХЕМИ/ | K8: 1 | L8: 1 | O8: БОРНАЯ К-ТА 10Г. ДЕЗ.СР-ВО ПОР. (НДС 20%) | P8: 22 | Q8: =(P8/5)*30 -> 132 | R8: =Q8/SUM($Q$4:$Q$806) -> 0.013674271 | S8: =R8+S7 -> 0.10939416 | T8: =IF(S8<0.8,"A", IF(S8<0.95,"B","C")) -> A | V8: БОРНАЯ К-ТА 10Г. ДЕЗ.СР-ВО ПОР. (НДС 20%) | W8: A
A9: 44774 | B9: КО-ВАМЛОСЕТ 5МГ.+160МГ.+12,5МГ. №30 ТАБ. П/П/О | C9: 1 | F9: L-ТИРОКСИН 50МКГ. №50 ТАБ. /БЕРЛИН ХЕМИ/ | G9: 1 | J9: 1 | L9: 2 | O9: ГЕМАТОГЕН РУССКИЙ ДЕТСКИЙ 40Г. ПЛИТКА /ФАРМ-ПРО/ | P9: 17 | Q9: =(P9/5)*30 -> 102 | R9: =Q9/SUM($Q$4:$Q$806) -> 0.010566482 | S9: =R9+S8 -> 0.11996065 | T9: =IF(S9<0.8,"A", IF(S9<0.95,"B","C")) -> A | V9: ГЕМАТОГЕН РУССКИЙ ДЕТСКИЙ 40Г. ПЛИТКА /ФАРМ-ПРО/ | W9: A
A10: 44774 | B10: АТОРВАСТАТИН-СЗ 20МГ. №60 ТАБ. П/П/О /СЕВЕРНАЯ ЗВЕЗДА/ | C10: 1 | F10: L-ТИРОКСИН 75МКГ. №100 ТАБ. /БЕРЛИН ХЕМИ/ | G10: 2 | J10: 1 | L10: 3 | O10: КОРВАЛОЛ 25МЛ. КАПЛИ Д/ПРИЕМА ВНУТРЬ ФЛ. И/У /ФАРМСТАНДАРТ ЛЕКСРЕДСТВА/ | P10: 14 | Q10: =(P10/5)*30 -> 84 | R10: =Q10/SUM($Q$4:$Q$806) -> 0.0087018086 | S10: =R10+S9 -> 0.12866246 | T10: =IF(S10<0.8,"A", IF(S10<0.95,"B","C")) -> A | V10: КОРВАЛОЛ 25МЛ. КАПЛИ Д/ПРИЕМА ВНУТРЬ ФЛ. И/У /ФАРМСТАНДАРТ ЛЕКСРЕДСТВА/ | W10: A
A11: 44774 | B11: АТОРВАСТАТИН-СЗ 40МГ. №30 ТАБ. П/П/О /СЕВЕРНАЯ ЗВЕЗДА/ | C11: 1 | F11: NF ВАТА ХИРУРГ. СТЕР. 100Г. /НЬЮФАРМ/ | G11: 1 | L11: 1 | O11: ЛЕЙКОПЛАСТЫРЬ БАКТЕР. 4Х10 №1 /ВЕРОФАРМ/ | P11: 14 | Q11: =(P11/5)*30 -> 84 | R11: =Q11/SUM($Q$4:$Q$806) -> 0.0087018086 | S11: =R11+S10 -> 0.13736426 | T11: =IF(S11<0.8,"A", IF(S11<0.95,"B","C")) -> A | V11: ЛЕЙКОПЛАСТЫРЬ БАКТЕР. 4Х10 №1 /ВЕРОФАРМ/ | W11: A
A12: 44774 | B12: КСИМЕЛИН ЭКСТРА 84МКГ/ДОЗА+70МКГ/ДОЗА 10МЛ. №1 НАЗАЛ.СПРЕЙ ДОЗИР. ФЛ. | C12: 1 | F12: АДЖИСЕПТ МЕД+ЛИМОН №24 ТАБ. Д/РАСС. | I12: 1 | L12: 1 | O12: ЛЕЙКОПЛАСТЫРЬ БАКТЕР. 6X10 №1 /ВЕРОФАРМ/ | P12: 13 | Q12: =(P12/5)*30 -> 78 | R12: =Q12/SUM($Q$4:$Q$806) -> 0.0080802508 | S12: =R12+S11 -> 0.14544451 | T12: =IF(S12<0.8,"A", IF(S12<0.95,"B","C")) -> A | V12: ЛЕЙКОПЛАСТЫРЬ БАКТЕР. 6X10 №1 /ВЕРОФАРМ/ | W12: A
A13: 44774 | B13: NF ВАТА ХИРУРГ. СТЕР. 100Г. /НЬЮФАРМ/ | C13: 1 | F13: АДЖИСЕПТ МЕНТОЛ+ЭВКАЛИПТ №24 ТАБ. Д/РАСС. | H13: 1 | L13: 1 | O13: МЕНОВАЗИН 40МЛ. №1 СПИРТ. Р-Р Д/НАРУЖ.ПРИМ. ФЛ. /САМАРАМЕДПРОМ/ | P13: 13 | Q13: =(P13/5)*30 -> 78 | R13: =Q13/SUM($Q$4:$Q$806) -> 0.0080802508 | S13: =R13+S12 -> 0.15352477 | T13: =IF(S13<0.8,"A", IF(S13<0.95,"B","C")) -> A | V13: МЕНОВАЗИН 40МЛ. №1 СПИРТ. Р-Р Д/НАРУЖ.ПРИМ. ФЛ. /САМАРАМЕДПРОМ/ | W13: A
A14: 44774 | B14: СТОПСЕПТ ПЛЮС 90% 100МЛ. ДЕЗ.СР-ВО ФЛ. | C14: 1 | F14: АЕВИТ 200МГ. №20 КАПС. (БАД) /МЕЛИГЕН/ | I14: 1 | L14: 1 | O14: ПЕРЕКИСЬ ВОДОРОДА 3% 100МЛ. №1 Р-Р ДЕЗ.СР-ВО ФЛ. (НДС 20%) | P14: 13 | Q14: =(P14/5)*30 -> 78 | R14: =Q14/SUM($Q$4:$Q$806) -> 0.0080802508 | S14: =R14+S13 -> 0.16160502 | T14: =IF(S14<0.8,"A", IF(S14<0.95,"B","C")) -> A | V14: ПЕРЕКИСЬ ВОДОРОДА 3% 100МЛ. №1 Р-Р ДЕЗ.СР-ВО ФЛ. (НДС 20%) | W14: A
A15: 44774 | B15: ПАСКАЛЬ ШПРИЦ 3-Х КОМП. 2МЛ. С ИГЛОЙ 23G 0,6Х30ММ. №10 [PASCAL] | C15: 1 | F15: АЗАРГА 10МГ/МЛ.+5МГ/МЛ. 5МЛ. №1 ГЛ.КАПЛИ ФЛ./КАП. | G15: 1 | H15: 1 | L15: 2 | O15: РАУНАТИН 2МГ. №50 ТАБ. П/О /ЗДОРОВЬЕ/ | P15: 13 | Q15: =(P15/5)*30 -> 78 | R15: =Q15/SUM($Q$4:$Q$806) -> 0.0080802508 | S15: =R15+S14 -> 0.16968527 | T15: =IF(S15<0.8,"A", IF(S15<0.95,"B","C")) -> A | V15: РАУНАТИН 2МГ. №50 ТАБ. П/О /ЗДОРОВЬЕ/ | W15: A
A16: 44774 | B16: ПАСКАЛЬ ШПРИЦ 3-Х КОМП. 2МЛ. С ИГЛОЙ 23G 0,6Х30ММ. №10 [PASCAL] | C16: 1 | F16: АЗИТРОМИЦИН 500МГ. №3 КАПС. /ПРОИЗВОДСТВО МЕДИКАМЕНТОВ/ ПроМед/ | I16: 2 | L16: 2 | O16: Карта LOYALITY 0,01Р | P16: 12 | Q16: =(P16/5)*30 -> 72 | R16: =Q16/SUM($Q$4:$Q$806) -> 0.007458693 | S16: =R16+S15 -> 0.17714396 | T16: =IF(S16<0.8,"A", IF(S16<0.95,"B","C")) -> A | V16: Карта LOYALITY 0,01Р | W16: A
A17: 44774 | B17: КЛОТРИМАЗОЛ 1% 20Г. КРЕМ Д/НАРУЖ.ПРИМ. ТУБА /ХИПЕРИОН/РУМЫНИЯ/ | C17: 1 | F17: АЙДИ ПРОТЕКТ ПЕЛЕНКИ ОДНОР. ВПИТ. 60Х90 №10 [ID] | I17: 1 | L17: 1 | O17: КОНТЕЙНЕР Д/СБОРА БИОМАТЕРИАЛА 100МЛ. СТЕР. (БАНКА) | P17: 11 | Q17: =(P17/5)*30 -> 66 | R17: =Q17/SUM($Q$4:$Q$806) -> 0.0068371353 | S17: =R17+S16 -> 0.1839811 | T17: =IF(S17<0.8,"A", IF(S17<0.95,"B","C")) -> A | V17: КОНТЕЙНЕР Д/СБОРА БИОМАТЕРИАЛА 100МЛ. СТЕР. (БАНКА) | W17: A
A18: 44774 | B18: РИНОНОРМ-ТЕВА 0,1% 140МКГ/ДОЗА 20МЛ. НАЗАЛ.СПРЕЙ ФЛ. /ТЕВА/ | C18: 1 | F18: АКВА МАРИС НОРМ ИНТЕНСИВ. ПРОМЫВАНИЕ 150МЛ. НАЗАЛ.СПРЕЙ | J18: 1 | L18: 1 | O18: ОМЕПРАЗОЛ 20МГ. №30 КАПС. /ПРОИЗВОДСТВО МЕДИКАМЕНТОВ/ | P18: 11 | Q18: =(P18/5)*30 -> 66 | R18: =Q18/SUM($Q$4:$Q$806) -> 0.0068371353 | S18: =R18+S17 -> 0.19081823 | T18: =IF(S18<0.8,"A", IF(S18<0.95,"B","C")) -> A | V18: ОМЕПРАЗОЛ 20МГ. №30 КАПС. /ПРОИЗВОДСТВО МЕДИКАМЕНТОВ/ | W18: A
A19: 44774 | B19: РИНОНОРМ-ТЕВА 0,1% 140МКГ/ДОЗА 20МЛ. НАЗАЛ.СПРЕЙ ФЛ. /ТЕВА/ | C19: 1 | F19: АКВА ЭЙР МОРЕ 50МЛ. НАЗАЛ.СПРЕЙ ФЛ. | K19: 1 | L19: 1 | O19: ТАУФОН 4% 10МЛ. №1 ГЛ.КАПЛИ ФЛ./КАП. /ОТИСИФАРМ/ФАРМСТАНДАРТ/ | P19: 11 | Q19: =(P19/5)*30 -> 66 | R19: =Q19/SUM($Q$4:$Q$806) -> 0.0068371353 | S19: =R19+S18 -> 0.19765537 | T19: =IF(S19<0.8,"A", IF(S19<0.95,"B","C")) -> A | V19: ТАУФОН 4% 10МЛ. №1 ГЛ.КАПЛИ ФЛ./КАП. /ОТИСИФАРМ/ФАРМСТАНДАРТ/ | W19: A
A20: 44774 | B20: ДЮФАЛАК 667МГ/МЛ. 500МЛ. СИРОП ФЛ. +МЕРН.СТАКАН /ЭББОТТ/СОЛВЕЙ/ | C20: 1 | F20: АКВАДЕТРИМ 15000МЕ/МЛ. 10МЛ. КАПЛИ Д/ПРИЕМА ВНУТРЬ ФЛ./КАП. (ВИТАМИН Д3 ВОДН.Р-Р) /МЕДАНА/ | K20: 1 | L20: 1 | O20: ПЕНТАЛГИН №24 ТАБ. П/П/О /ОТИСИФАРМ/ | P20: 10 | Q20: =(P20/5)*30 -> 60 | R20: =Q20/SUM($Q$4:$Q$806) -> 0.0062155775 | S20: =R20+S19 -> 0.20387094 | T20: =IF(S20<0.8,"A", IF(S20<0.95,"B","C")) -> A | V20: ПЕНТАЛГИН №24 ТАБ. П/П/О /ОТИСИФАРМ/ | W20: A
A21: 44774 | B21: ГЕЛАДРИНК ФОРТЕ ПОР. Д/ПРИЕМА ВНУТРЬ АПЕЛЬСИН 420Г. БАНКА | C21: 1 | F21: АКВАЛОР ЭКСТРА ФОРТЕ 150МЛ. АЛОЭ+РОМАШКА НАЗАЛ.СПРЕЙ | H21: 1 | L21: 1 | O21: УГОЛЬ АКТИВИРОВАННЫЙ 250МГ. №50 ТАБ. /ФАРМСТАНДАРТ ЛЕКСРЕДСТВА/ | P21: 10 | Q21: =(P21/5)*30 -> 60 | R21: =Q21/SUM($Q$4:$Q$806) -> 0.0062155775 | S21: =R21+S20 -> 0.21008652 | T21: =IF(S21<0.8,"A", IF(S21<0.95,"B","C")) -> A | V21: УГОЛЬ АКТИВИРОВАННЫЙ 250МГ. №50 ТАБ. /ФАРМСТАНДАРТ ЛЕКСРЕДСТВА/ | W21: A
A22: 44774 | B22: ПИРАЦЕТАМ 200МГ. №60 ТАБ. П/П/О /ОБНОВЛЕНИЕ/ | C22: 1 | F22: АККУ-ЧЕК ТЕСТ-ПОЛОСКИ ПЕРФОРМА №100 (50Х2) [ACCU-CHEK] | I22: 0.5 | L22: 0.5 | O22: ЦЕФТРИАКСОН 1Г. №1 ПОР. Д/Р-РА Д/В/В,В/М ФЛ. /ПРОМОМЕД/БИОХИМИК/ | P22: 10 | Q22: =(P22/5)*30 -> 60 | R22: =Q22/SUM($Q$4:$Q$806) -> 0.0062155775 | S22: =R22+S21 -> 0.2163021 | T22: =IF(S22<0.8,"A", IF(S22<0.95,"B","C")) -> A | V22: ЦЕФТРИАКСОН 1Г. №1 ПОР. Д/Р-РА Д/В/В,В/М ФЛ. /ПРОМОМЕД/БИОХИМИК/ | W22: A
A23: 44774 | B23: МАГНЕЛИС В6 №120 ТАБ. П/О | C23: 1 | F23: АКРИДЕРМ 0,05% 30Г. №1 КРЕМ Д/НАРУЖ.ПРИМ. ТУБА /АКРИХИН/ | H23: 1 | L23: 1 | O23: КОНКОР КОР 2,5МГ. №30 ТАБ. П/П/О /МЕРК/ | P23: 9 | Q23: =(P23/5)*30 -> 54 | R23: =Q23/SUM($Q$4:$Q$806) -> 0.0055940198 | S23: =R23+S22 -> 0.22189612 | T23: =IF(S23<0.8,"A", IF(S23<0.95,"B","C")) -> A | V23: КОНКОР КОР 2,5МГ. №30 ТАБ. П/П/О /МЕРК/ | W23: A
A24: 44774 | B24: МЕЗИМ-ФОРТЕ №80 ТАБ. П/О /БЕРЛИН-ХЕМИ/ | C24: 1 | F24: АКРИДЕРМ 0,05% 30Г. №1 МАЗЬ Д/НАРУЖ.ПРИМ. ТУБА /АКРИХИН/ | I24: 1 | L24: 1 | O24: ЛОПЕРАМИД-АКРИХИН 2МГ. №20 КАПС. /АКРИХИН/ | P24: 9 | Q24: =(P24/5)*30 -> 54 | R24: =Q24/SUM($Q$4:$Q$806) -> 0.0055940198 | S24: =R24+S23 -> 0.22749014 | T24: =IF(S24<0.8,"A", IF(S24<0.95,"B","C")) -> A | V24: ЛОПЕРАМИД-АКРИХИН 2МГ. №20 КАПС. /АКРИХИН/ | W24: A
A25: 44774 | B25: КАЛЬЦИЙ Д3 НИКОМЕД 500МГ.+200МЕ №60 КЛУБНИКА+АРБУЗ ТАБ.ЖЕВ. | C25: 1 | F25: АКРИДЕРМ ГК 0,05%+0,1%+1% 30Г. №1 КРЕМ Д/НАРУЖ.ПРИМ. ТУБА /АКРИХИН/ | K25: 1 | L25: 1 | O25: ОМЕЗ 20МГ. №30 КАПС. /Д-Р РЕДДИ/ | P25: 9 | Q25: =(P25/5)*30 -> 54 | R25: =Q25/SUM($Q$4:$Q$806) -> 0.0055940198 | S25: =R25+S24 -> 0.23308416 | T25: =IF(S25<0.8,"A", IF(S25<0.95,"B","C")) -> A | V25: ОМЕЗ 20МГ. №30 КАПС. /Д-Р РЕДДИ/ | W25: A
A26: 44774 | B26: ЭКСПРЕСС-ТЕСТ НА А/ТЕЛА COVID-19 LGG/LGM | C26: 2 | F26: АКТОВЕГИН 40МГ/МЛ. 2МЛ. №25 Р-Р Д/ИН. АМП. | K26: 0.2 | L26: 0.2 | O26: ЦЕФТРИАКСОН 1Г. №1 ПОР. Д/Р-РА Д/В/В,В/М ФЛ. /БИОСИНТЕЗ/ | P26: 9 | Q26: =(P26/5)*30 -> 54 | R26: =Q26/SUM($Q$4:$Q$806) -> 0.0055940198 | S26: =R26+S25 -> 0.23867818 | T26: =IF(S26<0.8,"A", IF(S26<0.95,"B","C")) -> A | V26: ЦЕФТРИАКСОН 1Г. №1 ПОР. Д/Р-РА Д/В/В,В/М ФЛ. /БИОСИНТЕЗ/ | W26: A
A27: 44774 | B27: БОБС ЛЕДЕНЦЫ Д/ГОРЛА 35Г. ЭКСТРА МЕНТОЛ №10 | C27: 1 | F27: АКТОВЕГИН 40МГ/МЛ. 5МЛ. №5 Р-Р Д/ИН. АМП. | J27: 1 | L27: 1 | O27: АСЕПТИКА САЛФЕТКА СПИРТОВАЯ 60Х100 №20 | P27: 8 | Q27: =(P27/5)*30 -> 48 | R27: =Q27/SUM($Q$4:$Q$806) -> 0.004972462 | S27: =R27+S26 -> 0.24365064 | T27: =IF(S27<0.8,"A", IF(S27<0.95,"B","C")) -> A | V27: АСЕПТИКА САЛФЕТКА СПИРТОВАЯ 60Х100 №20 | W27: A
A28: 44774 | B28: ЦИТРАМОН П №10 ТАБ. /ФАРМСТАНДАРТ/ | C28: 1 | F28: АКУЛИЙ ЖИР ГЕЛЬ-БАЛЬЗАМ Д/ТЕЛА ОКОПНИК+САБЕЛЬНИК 125МЛ. | I28: 1 | L28: 1 | O28: ВАЛЕРИАНЫ НАСТОЙКА 25МЛ. ФЛ. /ГИППОКРАТ/ | P28: 8 | Q28: =(P28/5)*30 -> 48 | R28: =Q28/SUM($Q$4:$Q$806) -> 0.004972462 | S28: =R28+S27 -> 0.2486231 | T28: =IF(S28<0.8,"A", IF(S28<0.95,"B","C")) -> A | V28: ВАЛЕРИАНЫ НАСТОЙКА 25МЛ. ФЛ. /ГИППОКРАТ/ | W28: A
A29: 44774 | B29: ЦИТРАМОН П №10 ТАБ. /ФАРМСТАНДАРТ/ | C29: 1 | F29: АЛЕРАНА ВИТАМИННО-МИНЕРАЛЬНЫЙ КОМПЛЕКС ДЕНЬ-НОЧЬ №60 ТАБ. [ALERANA] | I29: 1 | L29: 1 | O29: МАСКА МЕД. ТРЕХСЛОЙНАЯ (3-Х) НА РЕЗИНКЕ №5 | P29: 8 | Q29: =(P29/5)*30 -> 48 | R29: =Q29/SUM($Q$4:$Q$806) -> 0.004972462 | S29: =R29+S28 -> 0.25359556 | T29: =IF(S29<0.8,"A", IF(S29<0.95,"B","C")) -> A | V29: МАСКА МЕД. ТРЕХСЛОЙНАЯ (3-Х) НА РЕЗИНКЕ №5 | W29: A
A30: 44774 | B30: ЦИТРАМОН П №10 ТАБ. /ФАРМСТАНДАРТ/ | C30: 1 | F30: АЛЛАПИНИН 25МГ. №30 ТАБ. /ВИЛАР/ | H30: 1 | L30: 1 | O30: ПАНКРЕАТИН 25ЕД №60 ТАБ.КШ/РАСТВ. П/О БАНКА /БИОСИНТЕЗ/ | P30: 7 | Q30: =(P30/5)*30 -> 42 | R30: =Q30/SUM($Q$4:$Q$806) -> 0.0043509043 | S30: =R30+S29 -> 0.25794647 | T30: =IF(S30<0.8,"A", IF(S30<0.95,"B","C")) -> A | V30: ПАНКРЕАТИН 25ЕД №60 ТАБ.КШ/РАСТВ. П/О БАНКА /БИОСИНТЕЗ/ | W30: A
A31: 44774 | B31: ТИЗИН КЛАССИК 0,1% 10МЛ. НАЗАЛ.СПРЕЙ ФЛ. /ДЖОНСОН/ | C31: 1 | F31: АЛЛЕРВЭЙ 5МГ. №10 ТАБ. П/О | I31: 1 | L31: 1 | O31: ПУСТЫРНИКА НАСТОЙКА 25МЛ. ФЛ. /ГИППОКРАТ/ | P31: 7 | Q31: =(P31/5)*30 -> 42 | R31: =Q31/SUM($Q$4:$Q$806) -> 0.0043509043 | S31: =R31+S30 -> 0.26229737 | T31: =IF(S31<0.8,"A", IF(S31<0.95,"B","C")) -> A | V31: ПУСТЫРНИКА НАСТОЙКА 25МЛ. ФЛ. /ГИППОКРАТ/ | W31: A
A32: 44774 | B32: ЛАКОМКА ПОМАДА ГИГИЕН. ЯГОДНЫЙ МИКС 2,8Г. /АВАНТА/ | C32: 1 | F32: АЛЛОХОЛ №50 ТАБ. П/О /ФАРМСТАНДАРТ/ | H32: 1 | L32: 1 | O32: ТАУРИН 4% 10МЛ. ГЛ.КАПЛИ ФЛ./КАП. /СЛАВЯНСКАЯ АПТЕКА/ | P32: 7 | Q32: =(P32/5)*30 -> 42 | R32: =Q32/SUM($Q$4:$Q$806) -> 0.0043509043 | S32: =R32+S31 -> 0.26664828 | T32: =IF(S32<0.8,"A", IF(S32<0.95,"B","C")) -> A | V32: ТАУРИН 4% 10МЛ. ГЛ.КАПЛИ ФЛ./КАП. /СЛАВЯНСКАЯ АПТЕКА/ | W32: A
A33: 44774 | B33: ОМЕЗ 20МГ. №30 КАПС. /Д-Р РЕДДИ/ | C33: 1 | F33: АЛМАГЕЛЬ А 170МЛ. №1 СУСП. Д/ПРИЕМА ВНУТРЬ ФЛ. /БАЛКАН ФАРМА-ТРОЯН/ | H33: 1 | L33: 1 | O33: ФЕРРОГЕМАТОГЕН 50Г. ПАСТИЛКА ЖЕВ. (ПЛИТКА) | P33: 7 | Q33: =(P33/5)*30 -> 42 | R33: =Q33/SUM($Q$4:$Q$806) -> 0.0043509043 | S33: =R33+S32 -> 0.27099918 | T33: =IF(S33<0.8,"A", IF(S33<0.95,"B","C")) -> A | V33: ФЕРРОГЕМАТОГЕН 50Г. ПАСТИЛКА ЖЕВ. (ПЛИТКА) | W33: A
A34: 44774 | B34: ЭВКАЛИПТ М №24 ПАСТИЛКИ | C34: 2 | F34: АЛЬФА НОРМИКС 200МГ. №12 ТАБ. П/П/О | K34: 1 | L34: 1 | O34: ХЕЛП БИНТ СТЕР. 7МХ14СМ И/У [HELP] | P34: 7 | Q34: =(P34/5)*30 -> 42 | R34: =Q34/SUM($Q$4:$Q$806) -> 0.0043509043 | S34: =R34+S33 -> 0.27535009 | T34: =IF(S34<0.8,"A", IF(S34<0.95,"B","C")) -> A | V34: ХЕЛП БИНТ СТЕР. 7МХ14СМ И/У [HELP] | W34: A
A35: 44774 | B35: АЗАРГА 10МГ/МЛ.+5МГ/МЛ. 5МЛ. №1 ГЛ.КАПЛИ ФЛ./КАП. | C35: 1 | F35: АЛЬФА НОРМИКС 200МГ. №28 ТАБ. П/П/О | H35: 1 | L35: 1 | O35: ЭСВИЦИН СР-ВО П/ОБЛЫСЕНИЯ ЛОСЬОН-ТОНИК 250МЛ. ФЛ. /ВИО-ФАРМ/ | P35: 7 | Q35: =(P35/5)*30 -> 42 | R35: =Q35/SUM($Q$4:$Q$806) -> 0.0043509043 | S35: =R35+S34 -> 0.27970099 | T35: =IF(S35<0.8,"A", IF(S35<0.95,"B","C")) -> A | V35: ЭСВИЦИН СР-ВО П/ОБЛЫСЕНИЯ ЛОСЬОН-ТОНИК 250МЛ. ФЛ. /ВИО-ФАРМ/ | W35: A
A36: 44774 | B36: ТРАВАТАН 0,004% 2,5МЛ. №3 ГЛ.КАПЛИ ФЛ./КАП. | C36: 1 | F36: АЛЬФА ТОКОФЕРОЛА АЦЕТАТ 200МГ. №30 КАПС. (ВИТАМИН Е) /МИНСКИНТЕРКАПС/ | J36: 1 | L36: 1 | O36: АСКОРБИНКА ЛУНТИК ВИТ.С №10 ТАБ. (30Г.) /ФАРМ-ПРО/ТИГОДА-ФАРМ/ | P36: 6 | Q36: =(P36/5)*30 -> 36 | R36: =Q36/SUM($Q$4:$Q$806) -> 0.0037293465 | S36: =R36+S35 -> 0.28343034 | T36: =IF(S36<0.8,"A", IF(S36<0.95,"B","C")) -> A | V36: АСКОРБИНКА ЛУНТИК ВИТ.С №10 ТАБ. (30Г.) /ФАРМ-ПРО/ТИГОДА-ФАРМ/ | W36: A
A37: 44774 | B37: ЙОДА 5% 10МЛ. СПИРТ. Р-Р ФЛ. /ЯРОСЛАВСКАЯ ФФ/ | C37: 1 | F37: АЛЬФАГАН Р 0,15% 5МЛ. ГЛ.КАПЛИ ФЛ./КАП. | H37: 1 | L37: 1 | O37: АСПАРКАМ №60 ТАБ. /ФАРМАПОЛ-ВОЛГА/ | P37: 6 | Q37: =(P37/5)*30 -> 36 | R37: =Q37/SUM($Q$4:$Q$806) -> 0.0037293465 | S37: =R37+S36 -> 0.28715968 | T37: =IF(S37<0.8,"A", IF(S37<0.95,"B","C")) -> A | V37: АСПАРКАМ №60 ТАБ. /ФАРМАПОЛ-ВОЛГА/ | W37: A
A38: 44774 | B38: ОМЕПРАЗОЛ 20МГ. №30 КАПС. /ПРОИЗВОДСТВО МЕДИКАМЕНТОВ/ | C38: 1 | F38: АЛЬФАПЛАСТИК ТРУБКА РЕКТАЛЬНАЯ ГАЗООТВОДНАЯ Д/НОВОРОЖД. №16 | I38: 1 | L38: 1 | O38: КЕТОРОЛ ЭКСПРЕСС 10МГ. №20 ТАБ. ДИСПЕРГ. /Д-Р РЕДДИС/ | P38: 6 | Q38: =(P38/5)*30 -> 36 | R38: =Q38/SUM($Q$4:$Q$806) -> 0.0037293465 | S38: =R38+S37 -> 0.29088903 | T38: =IF(S38<0.8,"A", IF(S38<0.95,"B","C")) -> A | V38: КЕТОРОЛ ЭКСПРЕСС 10МГ. №20 ТАБ. ДИСПЕРГ. /Д-Р РЕДДИС/ | W38: A
A39: 44774 | B39: ОМЕПРАЗОЛ 20МГ. №30 КАПС. /ПРОИЗВОДСТВО МЕДИКАМЕНТОВ/ | C39: 1 | F39: АМБРОКСОЛ-АЛСИ 30МГ. №30 ТАБ. /АЛСИ/ | J39: 1 | L39: 1 | O39: ПАСКАЛЬ ШПРИЦ 3-Х КОМП. 3МЛ. С ИГЛОЙ 22G 0,7Х40ММ. №10 [PASCAL] | P39: 6 | Q39: =(P39/5)*30 -> 36 | R39: =Q39/SUM($Q$4:$Q$806) -> 0.0037293465 | S39: =R39+S38 -> 0.29461838 | T39: =IF(S39<0.8,"A", IF(S39<0.95,"B","C")) -> A | V39: ПАСКАЛЬ ШПРИЦ 3-Х КОМП. 3МЛ. С ИГЛОЙ 22G 0,7Х40ММ. №10 [PASCAL] | W39: A
A40: 44774 | B40: ОМЕПРАЗОЛ 20МГ. №30 КАПС. /ПРОИЗВОДСТВО МЕДИКАМЕНТОВ/ | C40: 1 | F40: АМЕЛИЯ ВАТА МЕД. ХИРУРГ. Н/СТЕР. 25Г. | I40: 1 | L40: 1 | O40: ПУСТЫРНИКА ЭКСТРАКТ 14МГ. №50 ТАБ. /ФАРМСТАНДАРТ/ | P40: 6 | Q40: =(P40/5)*30 -> 36 | R40: =Q40/SUM($Q$4:$Q$806) -> 0.0037293465 | S40: =R40+S39 -> 0.29834772 | T40: =IF(S40<0.8,"A", IF(S40<0.95,"B","C")) -> A | V40: ПУСТЫРНИКА ЭКСТРАКТ 14МГ. №50 ТАБ. /ФАРМСТАНДАРТ/ | W40: A
A41: 44774 | B41: ПАКЕТ | C41: 1 | F41: АМЕЛОТЕКС 1% 50Г. №1 ГЕЛЬ Д/НАРУЖ.ПРИМ. ТУБА | H41: 1 | L41: 1 | O41: СВЯТОЙ ИСТОЧНИК ВОДА ПИТЬЕВАЯ 0,5Л. Н/ГАЗ. ПЭТ | P41: 6 | Q41: =(P41/5)*30 -> 36 | R41: =Q41/SUM($Q$4:$Q$806) -> 0.0037293465 | S41: =R41+S40 -> 0.30207707 | T41: =IF(S41<0.8,"A", IF(S41<0.95,"B","C")) -> A | V41: СВЯТОЙ ИСТОЧНИК ВОДА ПИТЬЕВАЯ 0,5Л. Н/ГАЗ. ПЭТ | W41: A
A42: 44774 | B42: ПАКЕТ | C42: 1 | F42: АМИКСИН 125МГ. №6 ТАБ. П/П/О /ОТИСИФАРМ/ФАРМСТАНДАРТ/ | H42: 1 | L42: 1 | O42: ТРОКСЕРУТИН ВРАМЕД 2% 40Г. ГЕЛЬ Д/НАРУЖ.ПРИМ. ТУБА /СОФАРМА/ | P42: 6 | Q42: =(P42/5)*30 -> 36 | R42: =Q42/SUM($Q$4:$Q$806) -> 0.0037293465 | S42: =R42+S41 -> 0.30580641 | T42: =IF(S42<0.8,"A", IF(S42<0.95,"B","C")) -> A | V42: ТРОКСЕРУТИН ВРАМЕД 2% 40Г. ГЕЛЬ Д/НАРУЖ.ПРИМ. ТУБА /СОФАРМА/ | W42: A
A43: 44774 | B43: ПАКЕТ | C43: 1 | F43: АМИНТАКС 35000МЕ+10000МЕ+35000МЕ №10 СУПП. ВАГ. | G43: 1 | L43: 1 | O43: ЦИТРАМОН П №20 ТАБ. /МЕДИСОРБ/ | P43: 6 | Q43: =(P43/5)*30 -> 36 | R43: =Q43/SUM($Q$4:$Q$806) -> 0.0037293465 | S43: =R43+S42 -> 0.30953576 | T43: =IF(S43<0.8,"A", IF(S43<0.95,"B","C")) -> A | V43: ЦИТРАМОН П №20 ТАБ. /МЕДИСОРБ/ | W43: A
A44: 44774 | B44: ПАКЕТ | C44: 1 | F44: АМИТРИПТИЛИН 25МГ. №50 ТАБ. /ОЗОН/ | I44: 1 | L44: 1 | O44: ЦИТРАМОН П №20 ТАБ. /ФАРМСТАНДАРТ/ | P44: 6 | Q44: =(P44/5)*30 -> 36 | R44: =Q44/SUM($Q$4:$Q$806) -> 0.0037293465 | S44: =R44+S43 -> 0.31326511 | T44: =IF(S44<0.8,"A", IF(S44<0.95,"B","C")) -> A | V44: ЦИТРАМОН П №20 ТАБ. /ФАРМСТАНДАРТ/ | W44: A
A45: 44774 | B45: ПАКЕТ | C45: 1 | F45: АМЛОДИПИН 10МГ. №60 ТАБ. /ВЕРТЕКС/ | G45: 1 | L45: 1 | O45: ЭНАЛАПРИЛ 5МГ. №20 ТАБ. /ХЕМОФАРМ/ | P45: 6 | Q45: =(P45/5)*30 -> 36 | R45: =Q45/SUM($Q$4:$Q$806) -> 0.0037293465 | S45: =R45+S44 -> 0.31699445 | T45: =IF(S45<0.8,"A", IF(S45<0.95,"B","C")) -> A | V45: ЭНАЛАПРИЛ 5МГ. №20 ТАБ. /ХЕМОФАРМ/ | W45: A
A46: 44774 | B46: ПАКЕТ | C46: 1 | F46: АМЛОДИПИН 5МГ. №60 ТАБ. /ВЕРТЕКС/ | K46: 1 | L46: 1 | O46: АФОБАЗОЛ 10МГ. №60 ТАБ. | P46: 5 | Q46: =(P46/5)*30 -> 30 | R46: =Q46/SUM($Q$4:$Q$806) -> 0.0031077888 | S46: =R46+S45 -> 0.32010224 | T46: =IF(S46<0.8,"A", IF(S46<0.95,"B","C")) -> A | V46: АФОБАЗОЛ 10МГ. №60 ТАБ. | W46: A
A47: 44774 | B47: ПАКЕТ | C47: 1 | F47: АМЛОДИПИН-ТЕВА 5МГ. №30 ТАБ. /ТЕВА/ | I47: 1 | L47: 1 | O47: АЦИКЛОВИР-БЕЛУПО 5% 10Г. №1 КРЕМ Д/НАРУЖ.ПРИМ. ТУБА /БЕЛУПО/ | P47: 5 | Q47: =(P47/5)*30 -> 30 | R47: =Q47/SUM($Q$4:$Q$806) -> 0.0031077888 | S47: =R47+S46 -> 0.32321003 | T47: =IF(S47<0.8,"A", IF(S47<0.95,"B","C")) -> A | V47: АЦИКЛОВИР-БЕЛУПО 5% 10Г. №1 КРЕМ Д/НАРУЖ.ПРИМ. ТУБА /БЕЛУПО/ | W47: A
A48: 44774 | B48: ПАКЕТ | C48: 1 | F48: АММИАК 100МГ/МЛ. 100МЛ. №1 Р-Р Д/НАРУЖ./ИНГ. ФЛ. /САМАРСКАЯ ФФ/ | H48: 1 | L48: 1 | O48: БРИЛЛИАНТОВЫЙ ЗЕЛЕН 1% 25МЛ. №1 СПИРТ. Р-Р Д/НАРУЖ.ПРИМ. ФЛ. /САМАРАМЕДПРОМ/ЖЕНЕЛ/ | P48: 5 | Q48: =(P48/5)*30 -> 30 | R48: =Q48/SUM($Q$4:$Q$806) -> 0.0031077888 | S48: =R48+S47 -> 0.32631782 | T48: =IF(S48<0.8,"A", IF(S48<0.95,"B","C")) -> A | V48: БРИЛЛИАНТОВЫЙ ЗЕЛЕН 1% 25МЛ. №1 СПИРТ. Р-Р Д/НАРУЖ.ПРИМ. ФЛ. /САМАРАМЕДПРОМ/ЖЕНЕЛ/ | W48: A
A49: 44774 | B49: ПАКЕТ | C49: 1 | F49: АМОКСИКЛАВ 250МГ.+62,5МГ/5МЛ. 25Г. 100МЛ. ПОР. Д/СУСП. Д/ПРИЕМА ВНУТРЬ ФЛ. +ПИПЕТ.ДОЗИР. /ЛЕК/ | H49: 1 | L49: 1 | O49: ВАЛИДОЛ 60МГ. №10 ТАБ. ПОДЪЯЗЫЧ. /ТАТХИМФАРМПРЕПАРАТЫ/ | P49: 5 | Q49: =(P49/5)*30 -> 30 | R49: =Q49/SUM($Q$4:$Q$806) -> 0.0031077888 | S49: =R49+S48 -> 0.32942561 | T49: =IF(S49<0.8,"A", IF(S49<0.95,"B","C")) -> A | V49: ВАЛИДОЛ 60МГ. №10 ТАБ. ПОДЪЯЗЫЧ. /ТАТХИМФАРМПРЕПАРАТЫ/ | W49: A
A50: 44774 | B50: ПАКЕТ | C50: 1 | F50: АМОКСИЦИЛЛИН 250МГ/5МЛ. 40Г. №1 ГРАН. Д/СУСП. Д/ПРИЕМА ВНУТРЬ ФЛ. /ХЕМОФАРМ/ | H50: 1 | L50: 1 | O50: ГЛИЦИН 100МГ. №100 ТАБ. ПОДЪЯЗЫЧ. /БИОТИКИ/ | P50: 5 | Q50: =(P50/5)*30 -> 30 | R50: =Q50/SUM($Q$4:$Q$806) -> 0.0031077888 | S50: =R50+S49 -> 0.3325334 | T50: =IF(S50<0.8,"A", IF(S50<0.95,"B","C")) -> A | V50: ГЛИЦИН 100МГ. №100 ТАБ. ПОДЪЯЗЫЧ. /БИОТИКИ/ | W50: A
A51: 44774 | B51: ПЕРЕКИСЬ ВОДОРОДА 3% 100МЛ. №1 Р-Р ДЕЗ.СР-ВО ФЛ. ПЛАСТ. /САМАРАМЕДПРОМ/ | C51: 2 | F51: АМОКСИЦИЛЛИН 500МГ. №16 КАПС. /ХЕМОФАРМ/ | H51: 1 | J51: 2 | L51: 3 | O51: ДОКТОР ПЕРЕЦ ЛЕЙКОПЛАСТ. ПЕРЦОВЫЙ 10X18 №1 ПЕРФ. /ВЕРОФАРМ/ | P51: 5 | Q51: =(P51/5)*30 -> 30 | R51: =Q51/SUM($Q$4:$Q$806) -> 0.0031077888 | S51: =R51+S50 -> 0.33564119 | T51: =IF(S51<0.8,"A", IF(S51<0.95,"B","C")) -> A | V51: ДОКТОР ПЕРЕЦ ЛЕЙКОПЛАСТ. ПЕРЦОВЫЙ 10X18 №1 ПЕРФ. /ВЕРОФАРМ/ | W51: A
A52: 44774 | B52: ХЕЛП БИНТ СТЕР. 7МХ14СМ И/У [HELP] | C52: 2 | F52: АМОКСИЦИЛЛИН САНДОЗ 1000МГ. №12 ТАБ. П/О БЛИСТЕР /САНДОЗ/ | H52: 2 | L52: 2 | O52: ДОКТОР ПЕРЕЦ ЛЕЙКОПЛАСТ. ПЕРЦОВЫЙ 6X10 №1 ПЕРФ. /ВЕРОФАРМ/ | P52: 5 | Q52: =(P52/5)*30 -> 30 | R52: =Q52/SUM($Q$4:$Q$806) -> 0.0031077888 | S52: =R52+S51 -> 0.33874898 | T52: =IF(S52<0.8,"A", IF(S52<0.95,"B","C")) -> A | V52: ДОКТОР ПЕРЕЦ ЛЕЙКОПЛАСТ. ПЕРЦОВЫЙ 6X10 №1 ПЕРФ. /ВЕРОФАРМ/ | W52: A
A53: 44774 | B53: БИНТ СТЕР. 10МХ16СМ И/У | C53: 1 | F53: АМОСИН 500МГ. №10 ТАБ. /ПОЛЛО/ | J53: 1 | L53: 1 | O53: КАЛЕНДУЛЫ НАСТОЙКА 25МЛ. ФЛ. /ГИППОКРАТ/ | P53: 5 | Q53: =(P53/5)*30 -> 30 | R53: =Q53/SUM($Q$4:$Q$806) -> 0.0031077888 | S53: =R53+S52 -> 0.34185676 | T53: =IF(S53<0.8,"A", IF(S53<0.95,"B","C")) -> A | V53: КАЛЕНДУЛЫ НАСТОЙКА 25МЛ. ФЛ. /ГИППОКРАТ/ | W53: A
A54: 44774 | B54: ПЕНТАЛГИН №24 ТАБ. П/П/О /ОТИСИФАРМ/ | C54: 1 | F54: АНАЛЬГИН 500МГ. №20 ТАБ. /ФАРМСТАНДАРТ/ | G54: 3 | L54: 3 | O54: ЛЮКСПЛАСТ ЛЕЙКОПЛАСТ. БАКТЕР. 19Х72ММ ПЕРФ. ТЕЛЕСН. ПОЛИМЕР. №10 [LUXPLAST] | P54: 5 | Q54: =(P54/5)*30 -> 30 | R54: =Q54/SUM($Q$4:$Q$806) -> 0.0031077888 | S54: =R54+S53 -> 0.34496455 | T54: =IF(S54<0.8,"A", IF(S54<0.95,"B","C")) -> A | V54: ЛЮКСПЛАСТ ЛЕЙКОПЛАСТ. БАКТЕР. 19Х72ММ ПЕРФ. ТЕЛЕСН. ПОЛИМЕР. №10 [LUXPLAST] | W54: A
A55: 44774 | B55: ПЕНТАЛГИН №24 ТАБ. П/П/О /ОТИСИФАРМ/ | C55: 1 | F55: АНАЛЬГИН 500МГ/МЛ. 2МЛ. №10 Р-Р Д/В/В,В/М АМП. /НОВОСИБХИМФАРМ/ | G55: 1 | L55: 1 | O55: ПАСКАЛЬ ШПРИЦ 3-Х КОМП. 5МЛ. С ИГЛОЙ 22G 0,7Х30ММ. №10 [PASCAL] | P55: 5 | Q55: =(P55/5)*30 -> 30 | R55: =Q55/SUM($Q$4:$Q$806) -> 0.0031077888 | S55: =R55+S54 -> 0.34807234 | T55: =IF(S55<0.8,"A", IF(S55<0.95,"B","C")) -> A | V55: ПАСКАЛЬ ШПРИЦ 3-Х КОМП. 5МЛ. С ИГЛОЙ 22G 0,7Х30ММ. №10 [PASCAL] | W55: A
A56: 44774 | B56: НАЙЗ АКТИВГЕЛЬ 1% 50Г. №1 ГЕЛЬ Д/НАРУЖ.ПРИМ. ТУБА | C56: 1 | F56: АНАУРЕТТЕ СПРЕЙ Д/ОЧИЩ. УШНОЙ ПОЛОСТИ 15МЛ. | G56: 1 | L56: 1 | O56: ПЕРЕКИСЬ ВОДОРОДА 3% 200МЛ. Р-Р ФЛ. ПЛАСТ. /ЛЕКАРЬ/ | P56: 5 | Q56: =(P56/5)*30 -> 30 | R56: =Q56/SUM($Q$4:$Q$806) -> 0.0031077888 | S56: =R56+S55 -> 0.35118013 | T56: =IF(S56<0.8,"A", IF(S56<0.95,"B","C")) -> A | V56: ПЕРЕКИСЬ ВОДОРОДА 3% 200МЛ. Р-Р ФЛ. ПЛАСТ. /ЛЕКАРЬ/ | W56: A
A57: 44774 | B57: ГУБКА ГЕМОСТАТ. КОЛЛАГЕН. С СЕРЕБРОМ 50Х50Х7ММ №10 /ЗЕЛЕНАЯ ДУБРАВА/ | C57: 1 | F57: АНГЕЛ ПОВЯЗКА ПЛАСТЫРНОГО ТИПА БАКТЕР. 9Х10СМ. №10 [ANGEL] | H57: 1 | L57: 1 | O57: СИНАФЛАН 0,025% 15Г. МАЗЬ Д/НАРУЖ.ПРИМ. ТУБА /МУРОМСКИЙ ЗАВОД/ | P57: 5 | Q57: =(P57/5)*30 -> 30 | R57: =Q57/SUM($Q$4:$Q$806) -> 0.0031077888 | S57: =R57+S56 -> 0.35428792 | T57: =IF(S57<0.8,"A", IF(S57<0.95,"B","C")) -> A | V57: СИНАФЛАН 0,025% 15Г. МАЗЬ Д/НАРУЖ.ПРИМ. ТУБА /МУРОМСКИЙ ЗАВОД/ | W57: A
A58: 44774 | B58: СТАТИН 1Г. №5 ПОР. ПАК. (Д/ОСТАНОВКИ КРОВОТЕЧЕНИЙ) | C58: 1 | F58: АНДИПАЛ №20 ТАБ. /ФАРМСТАНДАРТ-ЛЕКСРЕДСТВА/ | G58: 1 | L58: 1 | O58: ТЕТРАЦИКЛИНОВАЯ 1% 5Г. ГЛ. МАЗЬ ТУБА /ТАТХИМФАРМ/ | P58: 5 | Q58: =(P58/5)*30 -> 30 | R58: =Q58/SUM($Q$4:$Q$806) -> 0.0031077888 | S58: =R58+S57 -> 0.35739571 | T58: =IF(S58<0.8,"A", IF(S58<0.95,"B","C")) -> A | V58: ТЕТРАЦИКЛИНОВАЯ 1% 5Г. ГЛ. МАЗЬ ТУБА /ТАТХИМФАРМ/ | W58: A
A59: 44774 | B59: ВАЛОКОРДИН 20МЛ. КАПЛИ Д/ПРИЕМА ВНУТРЬ ФЛ./КАП. | C59: 1 | F59: АНТИПОЛИЦАЙ №4 КАРАМЕЛЬ ЛЕДЕНЦОВАЯ Б/САХ. | I59: 1 | L59: 1 | O59: АРБИДОЛ МАКСИМУМ 200МГ. №10 КАПС. /ОТИСИФАРМ/ФАРМСТАНДАРТ/ | P59: 4 | Q59: =(P59/5)*30 -> 24 | R59: =Q59/SUM($Q$4:$Q$806) -> 0.002486231 | S59: =R59+S58 -> 0.35988194 | T59: =IF(S59<0.8,"A", IF(S59<0.95,"B","C")) -> A | V59: АРБИДОЛ МАКСИМУМ 200МГ. №10 КАПС. /ОТИСИФАРМ/ФАРМСТАНДАРТ/ | W59: A
A60: 44774 | B60: L-ТИРОКСИН 100МКГ. №100 ТАБ. /БЕРЛИН ХЕМИ/ | C60: 1 | F60: АНТИ-ЭЙДЖ ВИТАМИН Д3 500МЕ 10МЛ. №1 МАСЛ. Р-Р Д/ПРИЕМА ВНУТРЬ ФЛ./КАП. /ЭВАЛАР/ [ANTI-AGE] | H60: 1 | L60: 1 | O60: АСКОРБИНКА ЛУНТИК ВИТ.С КЛУБНИКА №10 ТАБ. (30Г.) /ФАРМ-ПРО/ТИГОДА-ФАРМ/ | P60: 4 | Q60: =(P60/5)*30 -> 24 | R60: =Q60/SUM($Q$4:$Q$806) -> 0.002486231 | S60: =R60+S59 -> 0.36236817 | T60: =IF(S60<0.8,"A", IF(S60<0.95,"B","C")) -> A | V60: АСКОРБИНКА ЛУНТИК ВИТ.С КЛУБНИКА №10 ТАБ. (30Г.) /ФАРМ-ПРО/ТИГОДА-ФАРМ/ | W60: A
A61: 44774 | B61: КЕТОНАЛ 50МГ/МЛ. 2МЛ. №10 Р-Р Д/В/В,В/М АМП. /ЛЕК/ | C61: 1 | F61: АПИЗАРТРОН 20Г. №1 МАЗЬ Д/НАРУЖ. ПРИМ. ТУБА | H61: 1 | L61: 1 | O61: АСКОРБИНОВАЯ К-ТА 25МГ. ВИШНЯ №10 ТАБ. КРУТКА САХ. /АСКОПРОМ/ | P61: 4 | Q61: =(P61/5)*30 -> 24 | R61: =Q61/SUM($Q$4:$Q$806) -> 0.002486231 | S61: =R61+S60 -> 0.3648544 | T61: =IF(S61<0.8,"A", IF(S61<0.95,"B","C")) -> A | V61: АСКОРБИНОВАЯ К-ТА 25МГ. ВИШНЯ №10 ТАБ. КРУТКА САХ. /АСКОПРОМ/ | W61: A
A62: 44774 | B62: ВОЛЬТАРЕН 25МГ/МЛ. 3МЛ. №5 Р-Р Д/В/М АМП. /НОВАРТИС/ГЛАКСО/ | C62: 1 | F62: АРБИДОЛ МАКСИМУМ 200МГ. №10 КАПС. /ОТИСИФАРМ/ФАРМСТАНДАРТ/ | G62: 1 | H62: 2 | K62: 1 | L62: 4 | O62: АЦЕТИЛСАЛИЦИЛОВАЯ К-ТА 500МГ. №20 ТАБ. /ФАРМСТАНДАРТ/ | P62: 4 | Q62: =(P62/5)*30 -> 24 | R62: =Q62/SUM($Q$4:$Q$806) -> 0.002486231 | S62: =R62+S61 -> 0.36734063 | T62: =IF(S62<0.8,"A", IF(S62<0.95,"B","C")) -> A | V62: АЦЕТИЛСАЛИЦИЛОВАЯ К-ТА 500МГ. №20 ТАБ. /ФАРМСТАНДАРТ/ | W62: A
A63: 44774 | B63: ПАСКАЛЬ ШПРИЦ 3-Х КОМП. 3МЛ. С ИГЛОЙ 22G 0,7Х40ММ. №10 [PASCAL] | C63: 2 | F63: АРКОКСИА 90МГ. №28 ТАБ. П/П/О | G63: 1 | L63: 1 | O63: ВОДА 2МЛ. №10 Д/ИН. АМП. /ФАРМАСИНТЕЗ/ | P63: 4 | Q63: =(P63/5)*30 -> 24 | R63: =Q63/SUM($Q$4:$Q$806) -> 0.002486231 | S63: =R63+S62 -> 0.36982686 | T63: =IF(S63<0.8,"A", IF(S63<0.95,"B","C")) -> A | V63: ВОДА 2МЛ. №10 Д/ИН. АМП. /ФАРМАСИНТЕЗ/ | W63: A
A64: 44774 | B64: ШИПОВНИКА ПЛОДЫ 2Г. №20 ПАК. /КРАСНОГОРСК/ | C64: 1 | F64: АРТРАДОЛ 100МГ. №20 ЛИОФ. Д/Р-РА Д/В/М АМП. | I64: 1 | L64: 1 | O64: ГЛИЦИН 100МГ. №50 ТАБ. ПОДЪЯЗЫЧ. /БИОТИКИ/ | P64: 4 | Q64: =(P64/5)*30 -> 24 | R64: =Q64/SUM($Q$4:$Q$806) -> 0.002486231 | S64: =R64+S63 -> 0.37231309 | T64: =IF(S64<0.8,"A", IF(S64<0.95,"B","C")) -> A | V64: ГЛИЦИН 100МГ. №50 ТАБ. ПОДЪЯЗЫЧ. /БИОТИКИ/ | W64: A
A65: 44774 | B65: АСЕПТИКА САЛФЕТКА СПИРТОВАЯ 60Х100 №20 | C65: 1 | F65: АСЕПТА ПАРОДОНТАЛ ЗУБ.ПАСТА АКТИВ ПРОФИЛ. 75МЛ. | G65: 1 | L65: 1 | O65: ДЕТРАЛЕКС 1000МГ. №60 ТАБ. П/П/О | P65: 4 | Q65: =(P65/5)*30 -> 24 | R65: =Q65/SUM($Q$4:$Q$806) -> 0.002486231 | S65: =R65+S64 -> 0.37479933 | T65: =IF(S65<0.8,"A", IF(S65<0.95,"B","C")) -> A | V65: ДЕТРАЛЕКС 1000МГ. №60 ТАБ. П/П/О | W65: A
A66: 44774 | B66: АСЕПТИКА САЛФЕТКА СПИРТОВАЯ 60Х100 №20 | C66: 1 | F66: АСЕПТИКА САЛФЕТКА СПИРТОВАЯ 60Х100 №20 | G66: 2 | I66: 5 | J66: 1 | L66: 8 | O66: ДИКЛОФЕНАК 25МГ/МЛ. 3МЛ. №5 Р-Р Д/В/М ВВЕД. АМП. /ХЕМОФАРМ/ | P66: 4 | Q66: =(P66/5)*30 -> 24 | R66: =Q66/SUM($Q$4:$Q$806) -> 0.002486231 | S66: =R66+S65 -> 0.37728556 | T66: =IF(S66<0.8,"A", IF(S66<0.95,"B","C")) -> A | V66: ДИКЛОФЕНАК 25МГ/МЛ. 3МЛ. №5 Р-Р Д/В/М ВВЕД. АМП. /ХЕМОФАРМ/ | W66: A
A67: 44774 | B67: ПАРАЦЕТАМОЛ 500МГ. №20 ТАБ. /ФАРМСТАНДАРТ/ | C67: 1 | F67: АСКОРБИНКА ЛУНТИК ВИТ.С №10 ТАБ. (30Г.) /ФАРМ-ПРО/ТИГОДА-ФАРМ/ | G67: 1 | H67: 1 | I67: 1 | J67: 2 | K67: 1 | L67: 6 | O67: ИБУКЛИН 400МГ.+325МГ. №10 ТАБ. П/П/О | P67: 4 | Q67: =(P67/5)*30 -> 24 | R67: =Q67/SUM($Q$4:$Q$806) -> 0.002486231 | S67: =R67+S66 -> 0.37977179 | T67: =IF(S67<0.8,"A", IF(S67<0.95,"B","C")) -> A | V67: ИБУКЛИН 400МГ.+325МГ. №10 ТАБ. П/П/О | W67: A
A68: 44774 | B68: ПАРАЦЕТАМОЛ 500МГ. №20 ТАБ. /ФАРМСТАНДАРТ/ | C68: 1 | F68: АСКОРБИНКА ЛУНТИК ВИТ.С КЛУБНИКА №10 ТАБ. (30Г.) /ФАРМ-ПРО/ТИГОДА-ФАРМ/ | J68: 3 | K68: 1 | L68: 4 | O68: КЛОПИДОГРЕЛ-СЗ 75МГ. №28 ТАБ. П/П/О /СЕВЕРНАЯ ЗВЕЗДА/ | P68: 4 | Q68: =(P68/5)*30 -> 24 | R68: =Q68/SUM($Q$4:$Q$806) -> 0.002486231 | S68: =R68+S67 -> 0.38225802 | T68: =IF(S68<0.8,"A", IF(S68<0.95,"B","C")) -> A | V68: КЛОПИДОГРЕЛ-СЗ 75МГ. №28 ТАБ. П/П/О /СЕВЕРНАЯ ЗВЕЗДА/ | W68: A
A69: 44774 | B69: ЦИАНОКОБАЛАМИН 0,5МГ/МЛ. 1МЛ. №10 Р-Р Д/ИН. АМП. (ВИТАМИН В12) /ДАЛЬХИМФАРМ/ | C69: 1 | F69: АСКОРБИНОВАЯ К-ТА 100МГ.+877МГ. ГЛЮКОЗА №40 ТАБ. /ФАРМСТАНДАРТ/ | G69: 2 | L69: 2 | O69: ЛЕЙКОПЛАСТЫРЬ 2Х500 ТКАН.ОСНОВА КАТУШКА КАРТОН /ВЕРОФАРМ/ | P69: 4 | Q69: =(P69/5)*30 -> 24 | R69: =Q69/SUM($Q$4:$Q$806) -> 0.002486231 | S69: =R69+S68 -> 0.38474425 | T69: =IF(S69<0.8,"A", IF(S69<0.95,"B","C")) -> A | V69: ЛЕЙКОПЛАСТЫРЬ 2Х500 ТКАН.ОСНОВА КАТУШКА КАРТОН /ВЕРОФАРМ/ | W69: A
A70: 44774 | B70: Д.ТАЙСС АНГИ СЕПТ ЛИМОН №24 ТАБ. Д/РАСС. | C70: 1 | F70: АСКОРБИНОВАЯ К-ТА 2,5Г. №10 ПОР. /МЕЛИГЕН/ (БАД) | K70: 1 | L70: 1 | O70: МЕЗИМ-ФОРТЕ №80 ТАБ. П/О /БЕРЛИН-ХЕМИ/ | P70: 4 | Q70: =(P70/5)*30 -> 24 | R70: =Q70/SUM($Q$4:$Q$806) -> 0.002486231 | S70: =R70+S69 -> 0.38723048 | T70: =IF(S70<0.8,"A", IF(S70<0.95,"B","C")) -> A | V70: МЕЗИМ-ФОРТЕ №80 ТАБ. П/О /БЕРЛИН-ХЕМИ/ | W70: A
A71: 44774 | B71: ПРОПОСОЛ 25Г. СПРЕЙ Д/МЕСТ.ПРИМ. БАЛЛОН /АЛТАЙВИТАМИНЫ/ | C71: 1 | F71: АСКОРБИНОВАЯ К-ТА 25МГ. ВИШНЯ №10 ТАБ. КРУТКА САХ. /АСКОПРОМ/ | I71: 1 | J71: 2 | K71: 1 | L71: 4 | O71: МЕРИДИАН МОЧЕПРИЕМНИК ДЕТСКИЙ PD2200 200МЛ. [MERIDIAN] | P71: 4 | Q71: =(P71/5)*30 -> 24 | R71: =Q71/SUM($Q$4:$Q$806) -> 0.002486231 | S71: =R71+S70 -> 0.38971671 | T71: =IF(S71<0.8,"A", IF(S71<0.95,"B","C")) -> A | V71: МЕРИДИАН МОЧЕПРИЕМНИК ДЕТСКИЙ PD2200 200МЛ. [MERIDIAN] | W71: A
A72: 44774 | B72: ИНГАВИРИН 90МГ. №10 КАПС. /ВАЛЕНТА/ | C72: 1 | F72: АСКОРБИНОВАЯ К-ТА 25МГ. ЯБЛОКО №10 ТАБ. КРУТКА САХ. /АСКОПРОМ/ | H72: 1 | I72: 1 | K72: 1 | L72: 3 | O72: МЕТРОГИЛ ДЕНТА 20Г. №1 ГЕЛЬ СТОМАТ. ТУБА | P72: 4 | Q72: =(P72/5)*30 -> 24 | R72: =Q72/SUM($Q$4:$Q$806) -> 0.002486231 | S72: =R72+S71 -> 0.39220294 | T72: =IF(S72<0.8,"A", IF(S72<0.95,"B","C")) -> A | V72: МЕТРОГИЛ ДЕНТА 20Г. №1 ГЕЛЬ СТОМАТ. ТУБА | W72: A
A73: 44774 | B73: ДОРИТРИЦИН №10 ТАБ. Д/РАСС. | C73: 1 | F73: АСКОРБИНОВАЯ К-ТА 50МГ/МЛ. 2МЛ. №10 Р-Р Д/В/В,В/М АМП. /ДАЛЬХИМФАРМ/ | I73: 1 | L73: 1 | O73: МИДОКАЛМ 150МГ. №30 ТАБ. П/П/О /ГЕДЕОН РИХТЕР/ | P73: 4 | Q73: =(P73/5)*30 -> 24 | R73: =Q73/SUM($Q$4:$Q$806) -> 0.002486231 | S73: =R73+S72 -> 0.39468917 | T73: =IF(S73<0.8,"A", IF(S73<0.95,"B","C")) -> A | V73: МИДОКАЛМ 150МГ. №30 ТАБ. П/П/О /ГЕДЕОН РИХТЕР/ | W73: A
A74: 44774 | B74: ПИНОСОЛ 10МЛ. НАЗАЛ.КАПЛИ ФЛ./КАП. | C74: 1 | F74: АСПАРКАМ №60 ТАБ. /ФАРМАПОЛ-ВОЛГА/ | G74: 1 | H74: 3 | J74: 2 | L74: 6 | O74: НУРОФЕН ЭКСПРЕСС ФОРТЕ 400МГ. №20 КАПС. /РЕКИТТ БЕНКИЗЕР/ | P74: 4 | Q74: =(P74/5)*30 -> 24 | R74: =Q74/SUM($Q$4:$Q$806) -> 0.002486231 | S74: =R74+S73 -> 0.3971754 | T74: =IF(S74<0.8,"A", IF(S74<0.95,"B","C")) -> A | V74: НУРОФЕН ЭКСПРЕСС ФОРТЕ 400МГ. №20 КАПС. /РЕКИТТ БЕНКИЗЕР/ | W74: A
A75: 44774 | B75: РИНОФЛУИМУЦИЛ 10МЛ. СПРЕЙ НАЗАЛ. ФЛ. /ЗАМБОН/ | C75: 1 | F75: АСПЕРА СУПЕРЧИСТОТЕЛ 3МЛ. ФЛ. | G75: 1 | I75: 1 | L75: 2 | O75: ПАРАЦЕТАМОЛ 500МГ. №20 ТАБ. /ФАРМСТАНДАРТ/ | P75: 4 | Q75: =(P75/5)*30 -> 24 | R75: =Q75/SUM($Q$4:$Q$806) -> 0.002486231 | S75: =R75+S74 -> 0.39966164 | T75: =IF(S75<0.8,"A", IF(S75<0.95,"B","C")) -> A | V75: ПАРАЦЕТАМОЛ 500МГ. №20 ТАБ. /ФАРМСТАНДАРТ/ | W75: A
A76: 44774 | B76: ЮНИДОКС СОЛЮТАБ 100МГ. №10 ТАБ.ДИСПЕРГ. /АСТЕЛЛАС/ | C76: 1 | F76: АТАРАКС 25МГ. №25 ТАБ. П/П/О /ЮСБ ФАРМА/ | K76: 1 | L76: 1 | O76: СИЛЬВЕР КАПИТАН БАТОНЧИК КОКОС БЕЛ.ГЛАЗ. 50Г. | P76: 4 | Q76: =(P76/5)*30 -> 24 | R76: =Q76/SUM($Q$4:$Q$806) -> 0.002486231 | S76: =R76+S75 -> 0.40214787 | T76: =IF(S76<0.8,"A", IF(S76<0.95,"B","C")) -> A | V76: СИЛЬВЕР КАПИТАН БАТОНЧИК КОКОС БЕЛ.ГЛАЗ. 50Г. | W76: A
A77: 44774 | B77: ДЕЗЛОРАТАДИН-ВЕЛФАРМ 5МГ. №10 ТАБ. П/О | C77: 1 | F77: АТЕНОЛОЛ РЕНЕВАЛ 100МГ. №30 ТАБ. /ОБНОВЛЕНИЕ/ | H77: 2 | L77: 2 | O77: СНУП 0,1% 90МКГ/ДОЗА 15МЛ. НАЗАЛ.СПРЕЙ ФЛ. /ШТАДА/ | P77: 4 | Q77: =(P77/5)*30 -> 24 | R77: =Q77/SUM($Q$4:$Q$806) -> 0.002486231 | S77: =R77+S76 -> 0.4046341 | T77: =IF(S77<0.8,"A", IF(S77<0.95,"B","C")) -> A | V77: СНУП 0,1% 90МКГ/ДОЗА 15МЛ. НАЗАЛ.СПРЕЙ ФЛ. /ШТАДА/ | W77: A
A78: 44774 | B78: КАЛИНОВ РОДНИК ВОДА МИНЕР. 0,5Л. Н/ГАЗ. | C78: 1 | F78: АТЕНОЛОЛ РЕНЕВАЛ 50МГ. №30 ТАБ. /ОБНОВЛЕНИЕ/ | G78: 1 | J78: 1 | L78: 2 | O78: СТОПСЕПТ ПЛЮС 90% 100МЛ. ДЕЗ.СР-ВО ФЛ. | P78: 4 | Q78: =(P78/5)*30 -> 24 | R78: =Q78/SUM($Q$4:$Q$806) -> 0.002486231 | S78: =R78+S77 -> 0.40712033 | T78: =IF(S78<0.8,"A", IF(S78<0.95,"B","C")) -> A | V78: СТОПСЕПТ ПЛЮС 90% 100МЛ. ДЕЗ.СР-ВО ФЛ. | W78: A
A79: 44774 | B79: Карта LOYALITY 0,01Р | C79: 1 | F79: АТОПИК ГЕЛЬ Д/КУПАНИЯ С ГОЛОВЫ ДО ПЯТОК Д/ДЕТ. 0+ 200МЛ. ФЛ. [ATOPIC] | I79: 1 | L79: 1 | O79: СФМ СИСТЕМА Д/ПЕРЕЛИВ. ИНФУЗ. Р-РОВ №1 ПЛАСТ.ИГЛА [SFM] | P79: 4 | Q79: =(P79/5)*30 -> 24 | R79: =Q79/SUM($Q$4:$Q$806) -> 0.002486231 | S79: =R79+S78 -> 0.40960656 | T79: =IF(S79<0.8,"A", IF(S79<0.95,"B","C")) -> A | V79: СФМ СИСТЕМА Д/ПЕРЕЛИВ. ИНФУЗ. Р-РОВ №1 ПЛАСТ.ИГЛА [SFM] | W79: A
A80: 44774 | B80: Карта LOYALITY 0,01Р | C80: 1 | F80: АТОПИК КРЕМ Д/ЕЖЕДН. УХОДА Д/ДЕТ. 0+ 100МЛ. ФЛ. [ATOPIC] | I80: 1 | L80: 1 | O80: ЦИТРАМОН П №10 ТАБ. /ФАРМСТАНДАРТ/ | P80: 4 | Q80: =(P80/5)*30 -> 24 | R80: =Q80/SUM($Q$4:$Q$806) -> 0.002486231 | S80: =R80+S79 -> 0.41209279 | T80: =IF(S80<0.8,"A", IF(S80<0.95,"B","C")) -> A | V80: ЦИТРАМОН П №10 ТАБ. /ФАРМСТАНДАРТ/ | W80: A
A81: 44774 | B81: Карта LOYALITY 0,01Р | C81: 1 | F81: АТОПИК КРЕМ-СТИК УСПОКАИВАЮЩИЙ Д/ДЕТ. 0+ 4,9МЛ. ПЕНАЛ [ATOPIC] | I81: 1 | K81: 1 | L81: 2 | O81: L-ТИРОКСИН 75МКГ. №100 ТАБ. /БЕРЛИН ХЕМИ/ | P81: 3 | Q81: =(P81/5)*30 -> 18 | R81: =Q81/SUM($Q$4:$Q$806) -> 0.0018646733 | S81: =R81+S80 -> 0.41395746 | T81: =IF(S81<0.8,"A", IF(S81<0.95,"B","C")) -> A | V81: L-ТИРОКСИН 75МКГ. №100 ТАБ. /БЕРЛИН ХЕМИ/ | W81: A
A82: 44774 | B82: АУГМЕНТИН 200МГ.+28,5МГ/5МЛ. 7,7Г. 70МЛ. ПОР. Д/СУСП. Д/ПРИЕМА ВНУТРЬ ФЛ. /ГЛАКСО/ | C82: 1 | F82: АТОРВАСТАТИН-СЗ 10МГ. №60 ТАБ. П/П/О /СЕВЕРНАЯ ЗВЕЗДА/ | I82: 1 | L82: 1 | O82: АМОКСИЦИЛЛИН 500МГ. №16 КАПС. /ХЕМОФАРМ/ | P82: 3 | Q82: =(P82/5)*30 -> 18 | R82: =Q82/SUM($Q$4:$Q$806) -> 0.0018646733 | S82: =R82+S81 -> 0.41582214 | T82: =IF(S82<0.8,"A", IF(S82<0.95,"B","C")) -> A | V82: АМОКСИЦИЛЛИН 500МГ. №16 КАПС. /ХЕМОФАРМ/ | W82: A
A83: 44774 | B83: ГЕКСОРАЛ ТАБС №20 ТАБ. Д/РАСС. | C83: 1 | F83: АТОРВАСТАТИН-СЗ 20МГ. №30 ТАБ. П/П/О /СЕВЕРНАЯ ЗВЕЗДА/ | H83: 1 | L83: 1 | O83: АНАЛЬГИН 500МГ. №20 ТАБ. /ФАРМСТАНДАРТ/ | P83: 3 | Q83: =(P83/5)*30 -> 18 | R83: =Q83/SUM($Q$4:$Q$806) -> 0.0018646733 | S83: =R83+S82 -> 0.41768681 | T83: =IF(S83<0.8,"A", IF(S83<0.95,"B","C")) -> A | V83: АНАЛЬГИН 500МГ. №20 ТАБ. /ФАРМСТАНДАРТ/ | W83: A
A84: 44774 | B84: РОМАШКИ ЦВЕТКИ 1,5Г. №20 ПАК. /КРАСНОГОРСК/ | C84: 1 | F84: АТОРВАСТАТИН-СЗ 20МГ. №60 ТАБ. П/П/О /СЕВЕРНАЯ ЗВЕЗДА/ | G84: 1 | H84: 1 | L84: 2 | O84: АСКОРБИНОВАЯ К-ТА 25МГ. ЯБЛОКО №10 ТАБ. КРУТКА САХ. /АСКОПРОМ/ | P84: 3 | Q84: =(P84/5)*30 -> 18 | R84: =Q84/SUM($Q$4:$Q$806) -> 0.0018646733 | S84: =R84+S83 -> 0.41955148 | T84: =IF(S84<0.8,"A", IF(S84<0.95,"B","C")) -> A | V84: АСКОРБИНОВАЯ К-ТА 25МГ. ЯБЛОКО №10 ТАБ. КРУТКА САХ. /АСКОПРОМ/ | W84: A
A85: 44774 | B85: РОМАШКИ ЦВЕТКИ 1,5Г. №20 ПАК. /КРАСНОГОРСК/ | C85: 1 | F85: АТОРВАСТАТИН-СЗ 40МГ. №30 ТАБ. П/П/О /СЕВЕРНАЯ ЗВЕЗДА/ | G85: 1 | L85: 1 | O85: АУРА ВАТНЫЕ ДИСКИ №100 [AURA] | P85: 3 | Q85: =(P85/5)*30 -> 18 | R85: =Q85/SUM($Q$4:$Q$806) -> 0.0018646733 | S85: =R85+S84 -> 0.42141616 | T85: =IF(S85<0.8,"A", IF(S85<0.95,"B","C")) -> A | V85: АУРА ВАТНЫЕ ДИСКИ №100 [AURA] | W85: A
A86: 44774 | B86: НУРОФЕН 100МГ/5МЛ. 100МЛ. СУСП. КЛУБНИКА Д/ДЕТЕЙ ФЛ. /РЕКИТТ БЕНКИЗЕР/ | C86: 1 | F86: АТОРИС 20МГ. №30 ТАБ. П/П/О /KRKA/ | H86: 1 | L86: 1 | O86: БЕТАЛОК ЗОК 25МГ. №14 ТАБ.ПРОЛОНГ. П/О /АСТРА ЗЕНЕКА/ | P86: 3 | Q86: =(P86/5)*30 -> 18 | R86: =Q86/SUM($Q$4:$Q$806) -> 0.0018646733 | S86: =R86+S85 -> 0.42328083 | T86: =IF(S86<0.8,"A", IF(S86<0.95,"B","C")) -> A | V86: БЕТАЛОК ЗОК 25МГ. №14 ТАБ.ПРОЛОНГ. П/О /АСТРА ЗЕНЕКА/ | W86: A
A87: 44774 | B87: РАСТОРОПША №100 ТАБ. | C87: 1 | F87: АТОРИС 20МГ. №90 ТАБ. П/П/О /KRKA/ | I87: 1 | L87: 1 | O87: БИОВИТА ВОДА ПИТЬЕВАЯ СТРУКТУР. 0,6Л. Н/ГАЗ. [BIOVITA] | P87: 3 | Q87: =(P87/5)*30 -> 18 | R87: =Q87/SUM($Q$4:$Q$806) -> 0.0018646733 | S87: =R87+S86 -> 0.4251455 | T87: =IF(S87<0.8,"A", IF(S87<0.95,"B","C")) -> A | V87: БИОВИТА ВОДА ПИТЬЕВАЯ СТРУКТУР. 0,6Л. Н/ГАЗ. [BIOVITA] | W87: A
A88: 44774 | B88: 911-ВЕНОЛГОН ГЕЛЬ Д/НОГ ПРИ ТЯЖЕСТИ,БОЛИ,ОТЕКАХ 100МЛ. ТУБА | C88: 1 | F88: АУГМЕНТИН 200МГ.+28,5МГ/5МЛ. 7,7Г. 70МЛ. ПОР. Д/СУСП. Д/ПРИЕМА ВНУТРЬ ФЛ. /ГЛАКСО/ | G88: 1 | L88: 1 | O88: БИСАКОДИЛ-НИЖФАРМ 10МГ. №10 СУПП. РЕКТ. /НИЖФАРМ/ | P88: 3 | Q88: =(P88/5)*30 -> 18 | R88: =Q88/SUM($Q$4:$Q$806) -> 0.0018646733 | S88: =R88+S87 -> 0.42701018 | T88: =IF(S88<0.8,"A", IF(S88<0.95,"B","C")) -> A | V88: БИСАКОДИЛ-НИЖФАРМ 10МГ. №10 СУПП. РЕКТ. /НИЖФАРМ/ | W88: A
A89: 44774 | B89: КОНКОР КОР 2,5МГ. №30 ТАБ. П/П/О /МЕРК/ | C89: 1 | F89: АУРА ВАТНЫЕ ДИСКИ №100 [AURA] | G89: 3 | L89: 3 | O89: БИСОПРОЛОЛ 2,5МГ. №30 ТАБ. П/П/О /ВЕРТЕКС/ | P89: 3 | Q89: =(P89/5)*30 -> 18 | R89: =Q89/SUM($Q$4:$Q$806) -> 0.0018646733 | S89: =R89+S88 -> 0.42887485 | T89: =IF(S89<0.8,"A", IF(S89<0.95,"B","C")) -> A | V89: БИСОПРОЛОЛ 2,5МГ. №30 ТАБ. П/П/О /ВЕРТЕКС/ | W89: A
A90: 44774 | B90: КОНКОР КОР 2,5МГ. №30 ТАБ. П/П/О /МЕРК/ | C90: 1 | F90: АУРА ВАТНЫЕ ДИСКИ №120 [AURA] | G90: 2 | L90: 2 | O90: ВАЛОКОРДИН 20МЛ. КАПЛИ Д/ПРИЕМА ВНУТРЬ ФЛ./КАП. | P90: 3 | Q90: =(P90/5)*30 -> 18 | R90: =Q90/SUM($Q$4:$Q$806) -> 0.0018646733 | S90: =R90+S89 -> 0.43073952 | T90: =IF(S90<0.8,"A", IF(S90<0.95,"B","C")) -> A | V90: ВАЛОКОРДИН 20МЛ. КАПЛИ Д/ПРИЕМА ВНУТРЬ ФЛ./КАП. | W90: A
A91: 44774 | B91: БИСОПРОЛОЛ 2,5МГ. №60 ТАБ. П/О /ВЕРТЕКС/ | C91: 1 | F91: АУРА ВАТНЫЕ ДИСКИ №80 [AURA] | I91: 1 | L91: 1 | O91: ВАЛОСЕРДИН 25МЛ. КАПЛИ Д/ПРИЕМА ВНУТРЬ ФЛ. /МОСФАРМА/ | P91: 3 | Q91: =(P91/5)*30 -> 18 | R91: =Q91/SUM($Q$4:$Q$806) -> 0.0018646733 | S91: =R91+S90 -> 0.4326042 | T91: =IF(S91<0.8,"A", IF(S91<0.95,"B","C")) -> A | V91: ВАЛОСЕРДИН 25МЛ. КАПЛИ Д/ПРИЕМА ВНУТРЬ ФЛ. /МОСФАРМА/ | W91: A
A92: 44774 | B92: СНУП 0,1% 90МКГ/ДОЗА 15МЛ. НАЗАЛ.СПРЕЙ ФЛ. /ШТАДА/ | C92: 1 | F92: АУРА САЛФЕТКИ ВЛАЖН. А/БАКТЕР. №15 [AURA] | K92: 1 | L92: 1 | O92: ВЕРОШПИРОН 50МГ. №30 КАПС. /ГЕДЕОН РИХТЕР/ | P92: 3 | Q92: =(P92/5)*30 -> 18 | R92: =Q92/SUM($Q$4:$Q$806) -> 0.0018646733 | S92: =R92+S91 -> 0.43446887 | T92: =IF(S92<0.8,"A", IF(S92<0.95,"B","C")) -> A | V92: ВЕРОШПИРОН 50МГ. №30 КАПС. /ГЕДЕОН РИХТЕР/ | W92: A
A93: 44774 | B93: СНУП 0,1% 90МКГ/ДОЗА 15МЛ. НАЗАЛ.СПРЕЙ ФЛ. /ШТАДА/ | C93: 1 | F93: АФОБАЗОЛ 10МГ. №60 ТАБ. | G93: 1 | H93: 1 | J93: 2 | K93: 1 | L93: 5 | O93: ГЕПАРИНОВАЯ 25Г. МАЗЬ Д/НАРУЖ.ПРИМ. ТУБА /ЗЕЛЕНАЯ ДУБРАВА/ | P93: 3 | Q93: =(P93/5)*30 -> 18 | R93: =Q93/SUM($Q$4:$Q$806) -> 0.0018646733 | S93: =R93+S92 -> 0.43633354 | T93: =IF(S93<0.8,"A", IF(S93<0.95,"B","C")) -> A | V93: ГЕПАРИНОВАЯ 25Г. МАЗЬ Д/НАРУЖ.ПРИМ. ТУБА /ЗЕЛЕНАЯ ДУБРАВА/ | W93: A
A94: 44774 | B94: ПОЛИДЕКСА С ФЕНИЛЭФРИНОМ 15МЛ. НАЗАЛ.СПРЕЙ ФЛ. | C94: 1 | F94: АЦЕКАРДОЛ 100МГ. №30 ТАБ.КШ/РАСТВ. П/П/О /СИНТЕЗ/ | J94: 1 | L94: 1 | O94: ДЕЗЛОРАТАДИН-ВЕЛФАРМ 5МГ. №10 ТАБ. П/О | P94: 3 | Q94: =(P94/5)*30 -> 18 | R94: =Q94/SUM($Q$4:$Q$806) -> 0.0018646733 | S94: =R94+S93 -> 0.43819822 | T94: =IF(S94<0.8,"A", IF(S94<0.95,"B","C")) -> A | V94: ДЕЗЛОРАТАДИН-ВЕЛФАРМ 5МГ. №10 ТАБ. П/О | W94: A
A95: 44774 | B95: РЕГЕЦИН 15Г. ГЕЛЬ П/УГРЕВОЙ СЫПИ | C95: 1 | F95: АЦЕТИЛСАЛИЦИЛОВАЯ К-ТА 500МГ. №20 ТАБ. /ФАРМСТАНДАРТ/ | G95: 1 | H95: 1 | I95: 1 | K95: 1 | L95: 4 | O95: ДИАБЕТОН МВ 60МГ. №30 ТАБ. МОДИФ.ВЫСВ. /СЕРВЬЕ/ | P95: 3 | Q95: =(P95/5)*30 -> 18 | R95: =Q95/SUM($Q$4:$Q$806) -> 0.0018646733 | S95: =R95+S94 -> 0.44006289 | T95: =IF(S95<0.8,"A", IF(S95<0.95,"B","C")) -> A | V95: ДИАБЕТОН МВ 60МГ. №30 ТАБ. МОДИФ.ВЫСВ. /СЕРВЬЕ/ | W95: A
A96: 44774 | B96: ГЕМАТОГЕН РУССКИЙ ДЕТСКИЙ 40Г. ПЛИТКА /ФАРМ-ПРО/ | C96: 2 | F96: АЦИКЛОВИР-АКРИХИН 200МГ. №20 ТАБ. /АКРИХИН/ | H96: 2 | L96: 2 | O96: ДОЛГИТ 5% 100Г. КРЕМ Д/НАРУЖ.ПРИМ. ТУБА /ДОЛОРГИТ/ | P96: 3 | Q96: =(P96/5)*30 -> 18 | R96: =Q96/SUM($Q$4:$Q$806) -> 0.0018646733 | S96: =R96+S95 -> 0.44192756 | T96: =IF(S96<0.8,"A", IF(S96<0.95,"B","C")) -> A | V96: ДОЛГИТ 5% 100Г. КРЕМ Д/НАРУЖ.ПРИМ. ТУБА /ДОЛОРГИТ/ | W96: A
A97: 44774 | B97: ГЕМАТОГЕН РУССКИЙ ДЕТСКИЙ 40Г. ПЛИТКА /ФАРМ-ПРО/ | C97: 1 | F97: АЦИКЛОВИР-БЕЛУПО 400МГ. №35 ТАБ. П/О /БЕЛУПО/ | J97: 2 | L97: 2 | O97: ДОНОРМИЛ 15МГ. №30 ТАБ. П/П/О | P97: 3 | Q97: =(P97/5)*30 -> 18 | R97: =Q97/SUM($Q$4:$Q$806) -> 0.0018646733 | S97: =R97+S96 -> 0.44379224 | T97: =IF(S97<0.8,"A", IF(S97<0.95,"B","C")) -> A | V97: ДОНОРМИЛ 15МГ. №30 ТАБ. П/П/О | W97: A
A98: 44774 | B98: ТИАМИНА ХЛОРИД 50МГ/МЛ. 1МЛ. №10 Р-Р Д/В/М ВВЕД. АМП. (ВИТАМИН В1) /СТАТУСФАРМ/ЕРЕВАН.ФФ/ | C98: 1 | F98: АЦИКЛОВИР-БЕЛУПО 5% 10Г. №1 КРЕМ Д/НАРУЖ.ПРИМ. ТУБА /БЕЛУПО/ | I98: 2 | J98: 2 | K98: 1 | L98: 5 | O98: ДЮФАЛАК 667МГ/МЛ. 1000МЛ. СИРОП ФЛ. +МЕРН.СТАКАН /ЭББОТТ/СОЛВЕЙ/ | P98: 3 | Q98: =(P98/5)*30 -> 18 | R98: =Q98/SUM($Q$4:$Q$806) -> 0.0018646733 | S98: =R98+S97 -> 0.44565691 | T98: =IF(S98<0.8,"A", IF(S98<0.95,"B","C")) -> A | V98: ДЮФАЛАК 667МГ/МЛ. 1000МЛ. СИРОП ФЛ. +МЕРН.СТАКАН /ЭББОТТ/СОЛВЕЙ/ | W98: A
A99: 44774 | B99: ТИАМИНА ХЛОРИД 50МГ/МЛ. 1МЛ. №10 Р-Р Д/В/М ВВЕД. АМП. (ВИТАМИН В1) /СТАТУСФАРМ/ЕРЕВАН.ФФ/ | C99: 1 | F99: АЦЦ-ЛОНГ 600МГ. №10 ШИП.ТАБ. /САНДОЗ/ | J99: 1 | L99: 1 | O99: ИБУПРОФЕН 200МГ. №50 ТАБ. П/О /БОРИСОВСКИЙ/ | P99: 3 | Q99: =(P99/5)*30 -> 18 | R99: =Q99/SUM($Q$4:$Q$806) -> 0.0018646733 | S99: =R99+S98 -> 0.44752158 | T99: =IF(S99<0.8,"A", IF(S99<0.95,"B","C")) -> A | V99: ИБУПРОФЕН 200МГ. №50 ТАБ. П/О /БОРИСОВСКИЙ/ | W99: A
A100: 44774 | B100: АРКОКСИА 90МГ. №28 ТАБ. П/П/О | C100: 1 | F100: АЭРТАЛ 100МГ. №60 ТАБ. П/П/О | I100: 0.66666666 | L100: 0.66666666 | O100: ИНГАВИРИН 90МГ. №10 КАПС. /ВАЛЕНТА/ | P100: 3 | Q100: =(P100/5)*30 -> 18 | R100: =Q100/SUM($Q$4:$Q$806) -> 0.0018646733 | S100: =R100+S99 -> 0.44938626 | T100: =IF(S100<0.8,"A", IF(S100<0.95,"B","C")) -> A | V100: ИНГАВИРИН 90МГ. №10 КАПС. /ВАЛЕНТА/ | W100: A
...

Sheet ИТОГ
A3: Названия | B3: Количество | C3: Сумма продаж | D3: Месячная рент. | E3: Итог
A4: ЛЕЙКОПЛАСТЫРЬ БАКТЕР. 2,5Х7,2 №1 /ВЕРОФАРМ/ | B4: A | C4: B | D4: A | E4: =B4&C4&D4 -> ABA
A5: НАФТИЗИН 0,1% 15МЛ. НАЗАЛ.КАПЛИ ФЛ./КАП. /СЛАВЯНСКАЯ АПТЕКА/ | B5: A | C5: B | D5: A | E5: =B5&C5&D5 -> ABA
A6: ПАКЕТ | B6: A | C6: C | D6: A | E6: =B6&C6&D6 -> ACA
A7: ВАЛИДОЛ 60МГ. №10 ТАБ. ПОДЪЯЗЫЧ. /ФАРМСТАНДАРТ/ | B7: A | C7: A | D7: A | E7: =B7&C7&D7 -> AAA
A8: БОРНАЯ К-ТА 10Г. ДЕЗ.СР-ВО ПОР. (НДС 20%) | B8: A | C8: B | D8: A | E8: =B8&C8&D8 -> ABA
A9: ГЕМАТОГЕН РУССКИЙ ДЕТСКИЙ 40Г. ПЛИТКА /ФАРМ-ПРО/ | B9: A | C9: B | D9: A | E9: =B9&C9&D9 -> ABA
A10: КОРВАЛОЛ 25МЛ. КАПЛИ Д/ПРИЕМА ВНУТРЬ ФЛ. И/У /ФАРМСТАНДАРТ ЛЕКСРЕДСТВА/ | B10: A | C10: A | D10: A | E10: =B10&C10&D10 -> AAA
A11: ЛЕЙКОПЛАСТЫРЬ БАКТЕР. 4Х10 №1 /ВЕРОФАРМ/ | B11: A | C11: C | D11: A | E11: =B11&C11&D11 -> ACA
A12: ЛЕЙКОПЛАСТЫРЬ БАКТЕР. 6X10 №1 /ВЕРОФАРМ/ | B12: A | C12: C | D12: A | E12: =B12&C12&D12 -> ACA
A13: МЕНОВАЗИН 40МЛ. №1 СПИРТ. Р-Р Д/НАРУЖ.ПРИМ. ФЛ. /САМАРАМЕДПРОМ/ | B13: A | C13: A | D13: A | E13: =B13&C13&D13 -> AAA
A14: ПЕРЕКИСЬ ВОДОРОДА 3% 100МЛ. №1 Р-Р ДЕЗ.СР-ВО ФЛ. (НДС 20%) | B14: A | C14: B | D14: A | E14: =B14&C14&D14 -> ABA
A15: РАУНАТИН 2МГ. №50 ТАБ. П/О /ЗДОРОВЬЕ/ | B15: A | C15: A | D15: A | E15: =B15&C15&D15 -> AAA
... A806: ХАРТМАНН КОСМОПОР Е ПОВЯЗКА 7,2Х5СМ №50 П/ОПЕР. САМОКЛ. СТЕР. /АРТ.9008705/ [HARTMANN COSMOPOR] | B806: C | C806: C | D806: C | E806: =B806&C806&D806 -> CCC
